Workbook
Name nproducto: [1]NPRODUCTOS!$J$9:$U$7009

Sheet CATASTRO Y PLANIFICACIÓN MP
A3: SERVICIO DE SALUD | B3: AYSEN
A5: NOMBRE ESTABLECIMIENTO | B5: Hospiotal Regional Coyhaique
A7: RESPONSABLE TÉCNICO | B7: Raul Aravena Turra | X7: MONITOREO MENSUAL DEL PLAN
X8: % EJECUCIÓN MP TOTAL MENSUAL | Y8: =+'TABLA CÁLCULO'!B24 -> 1 | Z8: =+'TABLA CÁLCULO'!C24 | AA8: =+'TABLA CÁLCULO'!D24 | AB8: =+'TABLA CÁLCULO'!E24 | AC8: =+'TABLA CÁLCULO'!F24 | AD8: =+'TABLA CÁLCULO'!G24 | AE8: =+'TABLA CÁLCULO'!H24 | AF8: =+'TABLA CÁLCULO'!I24 | ... AJ8: =+'TABLA CÁLCULO'!M24
A9: AÑO DE LEVANTAMIENTO | B9: 2026 | X9: % EJECUCIÓN MP EQC MENSUAL | Y9: =+'TABLA CÁLCULO'!B25 -> 1 | Z9: =+'TABLA CÁLCULO'!C25 | AA9: =+'TABLA CÁLCULO'!D25 | AB9: =+'TABLA CÁLCULO'!E25 | AC9: =+'TABLA CÁLCULO'!F25 | AD9: =+'TABLA CÁLCULO'!G25 | AE9: =+'TABLA CÁLCULO'!H25 | AF9: =+'TABLA CÁLCULO'!I25 | ... AJ9: =+'TABLA CÁLCULO'!M25
X10: % EJECUCIÓN MP EQR MENSUAL | Y10: =+'TABLA CÁLCULO'!B26 -> 1 | Z10: =+'TABLA CÁLCULO'!C26 | AA10: =+'TABLA CÁLCULO'!D26 | AB10: =+'TABLA CÁLCULO'!E26 | AC10: =+'TABLA CÁLCULO'!F26 | AD10: =+'TABLA CÁLCULO'!G26 | AE10: =+'TABLA CÁLCULO'!H26 | AF10: =+'TABLA CÁLCULO'!I26 | ... AJ10: =+'TABLA CÁLCULO'!M26
A11: GASTO PROGRAMADO MP | B11: 450000000 | D11: EJECUCIÓN GASTO MP | E11: 97382016 | X11: % EJECUCIÓN MP IM≥12 MENSUAL | Y11: =+'TABLA CÁLCULO'!B27 | Z11: =+'TABLA CÁLCULO'!C27 | AA11: =+'TABLA CÁLCULO'!D27 | AB11: =+'TABLA CÁLCULO'!E27 | AC11: =+'TABLA CÁLCULO'!F27 | AD11: =+'TABLA CÁLCULO'!G27 | AE11: =+'TABLA CÁLCULO'!H27 | AF11: =+'TABLA CÁLCULO'!I27 | ... AJ11: =+'TABLA CÁLCULO'!M27
A13: GASTO PROGRAMADO MC | B13: 400000000 | D13: EJECUCIÓN GASTO MC | E13: =+SUM('SEGUIMIENTO GASTO'!AG149:AG235) -> 15588666 | Q13: % EJECUCIÓN GASTO MP | T13: % EJECUCIÓN GASTO MC
Y14: CUMPLIMIENTO MANTENIMIENTO PREVENTIVO
A15: SERVICIO CLÍNICO | B15: RECINTO | C15: CLASE | D15: SUBCLASE | E15: NOMBRE EQUIPO | F15: MARCA | G15: MODELO | H15: SERIE | I15: N° INVENTARIO | J15: AÑO DE ADQUISICIÓN | K15: VIDA ÚTIL | L15: VIDA ÚTIL RESIDUAL | M15: PROPIO / ARRIENDO / COMODATO | N15: ESTADO (BUENO / REGULAR / MALO) | O15: CRÍTICO/ RELEVANTE / IM≥12 / NO APLICA | P15: EN GARANTÍA (SI / NO) | Q15: AÑO VENCIMIENTO GARANTÍA | R15: BAJO PLAN DE MANTENIMIENTO (SI / NO) | S15: AÑO INGRESO A PLAN DE MANTENIMIENTO (2023 / 2024 / 2025 / 2026) | T15: MANTENIMIENTO INTERNO O MANTENIMIENTO EXTERNO | U15: NOMBRE DE PROVEEDOR O MANTENIMIENTO INTERNO | V15: ID CONVENIO DE MANTENIMIENTO | W15: COSTO ANUAL DE MANTENIMIENTO SEGÚN CONVENIO / PRECIO DE REFERENCIA MANTENIMIENTO ANUAL | X15: FRECUENCIA ANUAL DE MANTENIMIENTO | Y15: ENERO | Z15: FEBRERO | AA15: MARZO | AB15: ABRIL | AC15: MAYO | AD15: JUNIO | AE15: JULIO | AF15: AGOSTO | AG15: SEPTIEMBRE | AH15: OCTUBRE | AI15: NOVIEMBRE | AJ15: DICIEMBRE
A16: Cirugía | B16: Hospital Regional Coyhaique | C16: monitoreo | D16: alto costo | E16: Monitor Desfibrilador | F16: Nihon Kohden | G16: TEC-5531E | H16: 02566 | I16: 0084-12 | J16: 2012 | K16: 10 | L16: =+IF(J16=0," ",K16-($B$9-J16)) -> -4 | M16: PROPIO | N16: MALO | O16: CRÍTICO | P16: NO | R16: SI | S16: 2026 | T16: Interna | U16: Interna | X16: 2 | AC16: X | AI16: X
A17: Medicina | B17: Hospital Regional Coyhaique | C17: monitoreo | D17: alto costo | E17: Monitor Desfibrilador | F17: Nihon Kohden | G17: TEC-5531E | H17: 02572 | I17: 0087-12 | J17: 2012 | K17: 10 | L17: =+IF(J17=0," ",K17-($B$9-J17)) -> -4 | M17: PROPIO | N17: MALO | O17: CRÍTICO | P17: NO | R17: SI | S17: 2026 | T17: Interna | U17: Interna | X17: 2 | AC17: X | AI17: X
A18: Maternidad | B18: Hospital Regional Coyhaique | C18: monitoreo | D18: alto costo | E18: Monitor Desfibrilador | F18: Nihon Kohden | G18: TEC-5531E | H18: 02583 | I18: 0086-12 | J18: 2012 | K18: 10 | L18: =+IF(J18=0," ",K18-($B$9-J18)) -> -4 | M18: PROPIO | N18: MALO | O18: CRÍTICO | P18: NO | R18: SI | S18: 2026 | T18: Interna | U18: Interna | X18: 2 | AC18: X | AI18: X
A19: Pediatria | B19: Hospital Regional Coyhaique | C19: monitoreo | D19: alto costo | E19: Monitor Desfibrilador | F19: Nihon Kohden | G19: TEC-5531E | H19: 02576 | I19: 0085-12 | J19: 2012 | K19: 10 | L19: =+IF(J19=0," ",K19-($B$9-J19)) -> -4 | M19: PROPIO | N19: MALO | O19: CRÍTICO | P19: NO | R19: SI | S19: 2026 | T19: Interna | U19: Interna | X19: 2 | AC19: X | AI19: X
A20: Pensionado | B20: Hospital Regional Coyhaique | C20: monitoreo | D20: alto costo | E20: Monitor Desfibrilador | F20: Nihon Kohden | G20: TEC-5531E | H20: 02567 | I20: 0088-12 | J20: 2012 | K20: 10 | L20: =+IF(J20=0," ",K20-($B$9-J20)) -> -4 | M20: PROPIO | N20: MALO | O20: CRÍTICO | P20: NO | R20: SI | S20: 2026 | T20: Interna | U20: Interna | X20: 2 | AC20: X | AI20: X
A21: Endoscopia | B21: Hospital Regional Coyhaique | C21: monitoreo | D21: alto costo | E21: Monitor Desfibrilador | F21: Nihon Kohden | G21: TEC-5531E | H21: 02485 | I21: 0031-12 | J21: 2012 | K21: 10 | L21: =+IF(J21=0," ",K21-($B$9-J21)) -> -4 | M21: PROPIO | N21: MALO | O21: CRÍTICO | P21: NO | R21: SI | S21: 2026 | T21: Interna | U21: Interna | X21: 2 | AC21: X | AI21: X
A22: Cardiologia | B22: Hospital Regional Coyhaique | C22: monitoreo | D22: alto costo | E22: Monitor Desfibrilador | F22: Nihon Kohden | G22: TEC-5531E | H22: 02486 | I22: 0030-12 | J22: 2012 | K22: 10 | L22: =+IF(J22=0," ",K22-($B$9-J22)) -> -4 | M22: PROPIO | N22: MALO | O22: CRÍTICO | P22: NO | R22: SI | S22: 2026 | T22: Interna | U22: Interna | X22: 2 | AC22: X | AI22: X
A23: Unidad Trat. Intermedio | B23: Hospital Regional Coyhaique | C23: monitoreo | D23: alto costo | E23: Monitor Desfibrilador | F23: Nihon Kohden | G23: TEC-5531E | H23: 02573 | I23: 0030-13 | J23: 2013 | K23: 10 | L23: =+IF(J23=0," ",K23-($B$9-J23)) -> -3 | M23: PROPIO | N23: MALO | O23: CRÍTICO | P23: NO | R23: SI | S23: 2026 | T23: Interna | U23: Interna | X23: 2 | AC23: X | AI23: X
A24: Uci adultos | B24: Hospital Regional Coyhaique | C24: monitoreo | D24: alto costo | E24: Monitor Desfibrilador | F24: Nihon Kohden | G24: TEC-5631E | H24: 00043 | I24: 0648-16 | J24: 2016 | K24: 10 | L24: =+IF(J24=0," ",K24-($B$9-J24)) -> 0 | M24: PROPIO | N24: MALO | O24: CRÍTICO | P24: NO | R24: SI | S24: 2026 | T24: Interna | U24: Interna | X24: 2 | AB24: X | AH24: X
A25: Uci adultos | B25: Hospital Regional Coyhaique | C25: monitoreo | D25: alto costo | E25: Monitor Desfibrilador | F25: Nihon Kohden | G25: TEC-5631E | H25: 00067 | I25: 0649-16 | J25: 2016 | K25: 10 | L25: =+IF(J25=0," ",K25-($B$9-J25)) -> 0 | M25: PROPIO | N25: MALO | O25: CRÍTICO | P25: NO | R25: SI | S25: 2026 | T25: Interna | U25: Interna | X25: 2 | AB25: X | AH25: X
A26: Policlínico de Especialidades / Vacunatorio | B26: Hospital Regional Coyhaique | C26: monitoreo | D26: alto costo | E26: Monitor Desfibrilador | F26: Zoll | G26: R Series | H26: AF12I024163 | I26: 0060-13 | J26: 2013 | K26: 10 | L26: =+IF(J26=0," ",K26-($B$9-J26)) -> -3 | M26: PROPIO | N26: MALO | O26: CRÍTICO | P26: NO | R26: SI | S26: 2026 | T26: Interna | U26: Interna | X26: 2 | Z26: X | AF26: X
A27: Dialisis | B27: Hospital Regional Coyhaique | C27: monitoreo | D27: alto costo | E27: Monitor Desfibrilador | F27: Zoll | G27: R Series | H27: AF17G068188 | I27: 1502-17 | J27: 2017 | K27: 10 | L27: =+IF(J27=0," ",K27-($B$9-J27)) -> 1 | M27: PROPIO | N27: MALO | O27: CRÍTICO | P27: NO | R27: SI | S27: 2026 | T27: Interna | U27: Interna | X27: 2 | Z27: X | AF27: X
A28: Pabellon quirurgico y anestesia | B28: Hospital Regional Coyhaique | C28: monitoreo | D28: alto costo | E28: Monitor Desfibrilador | F28: Zoll | G28: R Series | H28: AF13D028417 | I28: 0022-14 | J28: 2014 | K28: 10 | L28: =+IF(J28=0," ",K28-($B$9-J28)) -> -2 | M28: PROPIO | N28: MALO | O28: CRÍTICO | P28: NO | R28: SI | S28: 2026 | T28: Interna | U28: Interna | X28: 2 | Z28: X | AF28: X
A29: Pabellon quirurgico y anestesia | B29: Hospital Regional Coyhaique | C29: monitoreo | D29: alto costo | E29: Monitor Desfibrilador | F29: Zoll | G29: R Series | H29: AF13D028440 | I29: 0023-14 | J29: 2014 | K29: 10 | L29: =+IF(J29=0," ",K29-($B$9-J29)) -> -2 | M29: PROPIO | N29: MALO | O29: CRÍTICO | P29: NO | R29: SI | S29: 2026 | T29: Interna | U29: Interna | X29: 2 | Z29: X | AF29: X
A30: Ucin Neonatologia | B30: Hospital Regional Coyhaique | C30: monitoreo | D30: alto costo | E30: Monitor Desfibrilador | F30: Zoll | G30: R Series | H30: AF13H030686 | I30: 0024-14 | J30: 2014 | K30: 10 | L30: =+IF(J30=0," ",K30-($B$9-J30)) -> -2 | M30: PROPIO | N30: MALO | O30: CRÍTICO | P30: NO | R30: SI | S30: 2026 | T30: Interna | U30: Interna | X30: 2 | Z30: X | AF30: X
A31: Hospi. Domiciliaria | B31: Hospital Regional Coyhaique | C31: monitoreo | D31: alto costo | E31: Monitor Desfibrilador DEA | F31: Nihon Kohden | G31: AED 2100K | H31: 13046 | I31: 0423-15 | J31: 2015 | K31: 10 | L31: =+IF(J31=0," ",K31-($B$9-J31)) -> -1 | M31: PROPIO | N31: MALO | O31: CRÍTICO | P31: NO | R31: SI | S31: 2026 | T31: Interna | U31: Interna | X31: 2 | Y31: √ | AE31: X
A32: Pre-Parto | B32: Hospital Regional Coyhaique | C32: monitoreo | D32: alto costo | E32: Monitor Desfibrilador | F32: Nihon Kohden | G32: TEC-5631E | H32: 00029 | I32: 0647-16 | J32: 2016 | K32: 10 | L32: =+IF(J32=0," ",K32-($B$9-J32)) -> 0 | M32: PROPIO | N32: MALO | O32: CRÍTICO | P32: NO | R32: SI | S32: 2026 | T32: Interna | U32: Interna | X32: 2 | AB32: X | AH32: X
A33: Cardiologia | B33: Hospital Regional Coyhaique | C33: monitoreo | D33: alto costo | E33: Monitor Desfibrilador | F33: Nihon Kohden | G33: TEC-5631E | H33: 00038 | I33: 1162-17 | J33: 2017 | K33: 10 | L33: =+IF(J33=0," ",K33-($B$9-J33)) -> 1 | M33: PROPIO | N33: MALO | O33: CRÍTICO | P33: NO | R33: SI | S33: 2026 | T33: Interna | U33: Interna | X33: 2 | AB33: X | AH33: X
A34: Unidad Trat. Intermedio | B34: Hospital Regional Coyhaique | C34: monitoreo | D34: alto costo | E34: Monitor Desfibrilador | F34: Zoll | G34: M Series | H34: T08K107750 | I34: 1389 | K34: 10 | L34: =+IF(J34=0," ",K34-($B$9-J34)) | M34: PROPIO | N34: MALO | O34: CRÍTICO | P34: NO | R34: SI | S34: 2026 | T34: Interna | U34: Interna | X34: 2 | Z34: X | AF34: X
A35: Equipos Medicos | B35: Hospital Regional Coyhaique | C35: monitoreo | D35: alto costo | E35: Monitor Desfibrilador | F35: Nihon Kohden | G35: TEC-5521E | H35: 01543 | I35: 0030-11 | J35: 2011 | K35: 10 | L35: =+IF(J35=0," ",K35-($B$9-J35)) -> -5 | M35: PROPIO | N35: MALO | O35: CRÍTICO | P35: NO | R35: SI | S35: 2026 | T35: Interna | U35: Interna | X35: 2 | AB35: X | AH35: X
A36: UTI pediatrica | B36: Hospital Regional Coyhaique | C36: monitoreo | D36: alto costo | E36: Monitor Desfibrilador | F36: Zoll | G36: R Series | H36: AF15F047337 | I36: 0719-16 | J36: 2016 | K36: 10 | L36: =+IF(J36=0," ",K36-($B$9-J36)) -> 0 | M36: PROPIO | N36: MALO | O36: CRÍTICO | P36: NO | R36: SI | S36: 2026 | T36: Interna | U36: Interna | X36: 2 | Z36: X | AF36: X
A37: Pabellon quirurgico y anestesia | B37: Hospital Regional Coyhaique | C37: monitoreo | D37: alto costo | E37: Monitor Desfibrilador | F37: Zoll | G37: R Series | H37: AF18H083828 | I37: 17344 | J37: 2018 | K37: 10 | L37: =+IF(J37=0," ",K37-($B$9-J37)) -> 2 | M37: PROPIO | N37: MALO | O37: CRÍTICO | P37: NO | R37: SI | S37: 2026 | T37: Interna | U37: Interna | X37: 2 | AA37: X | AG37: X
A38: Pabellon quirurgico y anestesia | B38: Hospital Regional Coyhaique | C38: monitoreo | D38: alto costo | E38: Monitor Desfibrilador | F38: Zoll | G38: R Series | H38: AF18H083829 | I38: 17340 | J38: 2018 | K38: 10 | L38: =+IF(J38=0," ",K38-($B$9-J38)) -> 2 | M38: PROPIO | N38: MALO | O38: CRÍTICO | P38: NO | R38: SI | S38: 2026 | T38: Interna | U38: Interna | X38: 2 | AA38: X | AG38: X
A39: Pabellon quirurgico y anestesia | B39: Hospital Regional Coyhaique | C39: monitoreo | D39: alto costo | E39: Monitor Desfibrilador | F39: Zoll | G39: R Series | H39: AF19A090692 | I39: 17385 | J39: 2018 | K39: 10 | L39: =+IF(J39=0," ",K39-($B$9-J39)) -> 2 | M39: PROPIO | N39: MALO | O39: CRÍTICO | P39: NO | R39: SI | S39: 2026 | T39: Interna | U39: Interna | X39: 2 | Y39: √ | AE39: X
A40: Pabellon quirurgico y anestesia | B40: Hospital Regional Coyhaique | C40: monitoreo | D40: alto costo | E40: Monitor Desfibrilador | F40: Zoll | G40: R Series | H40: AF19A090702 | I40: 17386 | J40: 2018 | K40: 10 | L40: =+IF(J40=0," ",K40-($B$9-J40)) -> 2 | M40: PROPIO | N40: MALO | O40: CRÍTICO | P40: NO | R40: SI | S40: 2026 | T40: Interna | U40: Interna | X40: 2 | Y40: √ | AE40: X
A41: Medicina | B41: Hospital Regional Coyhaique | C41: monitoreo | D41: alto costo | E41: Monitor Desfibrilador | F41: Philips | G41: Efficia DFM100 | H41: CN32629235 | I41: 17961 | J41: 2018 | K41: 10 | L41: =+IF(J41=0," ",K41-($B$9-J41)) -> 2 | M41: PROPIO | N41: MALO | O41: CRÍTICO | P41: NO | R41: SI | S41: 2026 | T41: Interna | U41: Interna | X41: 2 | AC41: X | AI41: X
A42: Urgencia | B42: Hospital Regional Coyhaique | C42: monitoreo | D42: alto costo | E42: Monitor Desfibrilador | F42: Zoll | G42: M2 | H42: BA19C000002 | I42: 18039 | J42: 2020 | K42: 10 | L42: =+IF(J42=0," ",K42-($B$9-J42)) -> 4 | M42: PROPIO | N42: REGULAR | O42: CRÍTICO | P42: NO | R42: SI | S42: 2026 | T42: Interna | U42: Interna | X42: 2 | AD42: X | AJ42: X
A43: Urgencia | B43: Hospital Regional Coyhaique | C43: monitoreo | D43: alto costo | E43: Monitor Desfibrilador | F43: Zoll | G43: M2 | H43: BA20F000016 | I43: 18102 | J43: 2020 | K43: 10 | L43: =+IF(J43=0," ",K43-($B$9-J43)) -> 4 | M43: PROPIO | N43: REGULAR | O43: CRÍTICO | P43: NO | Q43: 03.08.21 | R43: SI | S43: 2026 | T43: Interna | U43: Interna | X43: 2 | Z43: X | AF43: X
A44: Urgencia | B44: Hospital Regional Coyhaique | C44: monitoreo | D44: alto costo | E44: Monitor Desfibrilador | F44: Zoll | G44: M2 | H44: BA20F000014 | I44: 18101 | J44: 2020 | K44: 10 | L44: =+IF(J44=0," ",K44-($B$9-J44)) -> 4 | M44: PROPIO | N44: REGULAR | O44: CRÍTICO | P44: NO | Q44: 03.08.21 | R44: SI | S44: 2026 | T44: Interna | U44: Interna | X44: 2 | Z44: X | AF44: X
A45: Imageonología (Resonador Magnetico) | B45: Hospital Regional Coyhaique | C45: monitoreo | D45: alto costo | E45: Monitor Desfibrilador | F45: CU Medical | G45: HD-1 | H45: M2S23G079 | I45: 18839 | J45: 2022 | K45: 10 | L45: =+IF(J45=0," ",K45-($B$9-J45)) -> 6 | M45: PROPIO | N45: BUENO | O45: CRÍTICO | P45: SI | Q45: 09.01.26 | R45: SI | S45: 2026 | T45: EXTERNO | U45: Medcasem (G) | X45: 2 | Y45: √ | AE45: X
A46: Urgencia Obstétrica | B46: Hospital Regional Coyhaique | C46: monitoreo | D46: alto costo | E46: Monitor Desfibrilador | F46: Bexen Cardio | G46: Reanibex 700 | H46: 20062322 | I46: 18970 | J46: 2023 | K46: 10 | L46: =+IF(J46=0," ",K46-($B$9-J46)) -> 7 | M46: PROPIO | N46: BUENO | O46: CRÍTICO | P46: NO | Q46: 08.03.25 | R46: SI | S46: 2026 | T46: Interna | U46: Interna | X46: 2 | AA46: X | AG46: X
A47: Imagenología (Sala Juno) | B47: Hospital Regional Coyhaique | C47: monitoreo | D47: alto costo | E47: Monitor Desfibrilador | F47: Bexen Cardio | G47: Reanibex 700 | H47: 20062323 | I47: 18975 | J47: 2023 | K47: 10 | L47: =+IF(J47=0," ",K47-($B$9-J47)) -> 7 | M47: PROPIO | N47: BUENO | O47: CRÍTICO | P47: NO | Q47: 08.03.25 | R47: SI | S47: 2026 | T47: Interna | U47: Interna | X47: 2 | AA47: X | AG47: X
A48: Salud Mental | B48: Hospital Regional Coyhaique | C48: monitoreo | D48: alto costo | E48: Monitor Desfibrilador | F48: Bexen Cardio | G48: Reanibex 700 | H48: 20062324 | I48: 18976 | J48: 2023 | K48: 10 | L48: =+IF(J48=0," ",K48-($B$9-J48)) -> 7 | M48: PROPIO | N48: BUENO | O48: CRÍTICO | P48: NO | Q48: 08.03.25 | R48: SI | S48: 2026 | T48: Interna | U48: Interna | X48: 2 | AA48: X | AG48: X
A49: Imagenología (Scanner) | B49: Hospital Regional Coyhaique | C49: monitoreo | D49: alto costo | E49: Monitor Desfibrilador | F49: Bexen Cardio | G49: Reanibex 700 | H49: 20062325 | I49: 18977 | J49: 2023 | K49: 10 | L49: =+IF(J49=0," ",K49-($B$9-J49)) -> 7 | M49: PROPIO | N49: BUENO | O49: CRÍTICO | P49: NO | Q49: 08.03.25 | R49: SI | S49: 2026 | T49: Interna | U49: Interna | X49: 2 | AA49: X | AG49: X
A50: Endoscopia | B50: Hospital Regional Coyhaique | C50: monitoreo | D50: alto costo | E50: Monitor Desfibrilador | F50: Mindray | G50: BeneHeart D3 | H50: EZ-2A099710 | I50: 18979 | J50: 2023 | K50: 10 | L50: =+IF(J50=0," ",K50-($B$9-J50)) -> 7 | M50: PROPIO | N50: BUENO | O50: CRÍTICO | P50: NO | Q50: 13.04.24 | R50: SI | S50: 2026 | T50: Interna | U50: Interna | X50: 2 | AB50: X | AH50: X
A51: Urg. Pediátrica | B51: Hospital Regional Coyhaique | C51: monitoreo | D51: alto costo | E51: Monitor Desfibrilador | F51: Zoll | G51: M2 | H51: BA23D000049 | I51: 19097 | J51: 2024 | K51: 10 | L51: =+IF(J51=0," ",K51-($B$9-J51)) -> 8 | M51: PROPIO | N51: BUENO | O51: CRÍTICO | P51: NO | Q51: 05.10.25 | R51: SI | S51: 2026 | T51: Interna | U51: Interna | X51: 2 | AB51: X | AH51: X
A52: Unidad Trat. Intermedio | B52: Hospital Regional Coyhaique | C52: monitoreo | D52: alto costo | E52: Monitor Desfibrilador | F52: Zoll | G52: M2 | H52: B424D000165 | I52: 19477 | J52: 2024 | K52: 10 | L52: =+IF(J52=0," ",K52-($B$9-J52)) -> 8 | M52: PROPIO | N52: BUENO | O52: CRÍTICO | P52: NO | R52: SI | S52: 2026 | T52: Interna | U52: Interna | X52: 2 | AA52: X | AG52: X
A53: Cirugía Mayor Ambulatoria | B53: Hospital Regional Coyhaique | C53: monitoreo | D53: alto costo | E53: Monitor Desfibrilador | F53: Zoll | G53: M2 | H53: B424D000204 | I53: 19478 | J53: 2024 | K53: 10 | L53: =+IF(J53=0," ",K53-($B$9-J53)) -> 8 | M53: PROPIO | N53: BUENO | O53: CRÍTICO | P53: NO | R53: SI | S53: 2026 | T53: Interna | U53: Interna | X53: 2 | AA53: X | AG53: X
A54: Oncología | B54: Hospital Regional Coyhaique | C54: monitoreo | D54: alto costo | E54: Monitor Desfibrilador | F54: Zoll | G54: M2 | H54: B424D000213 | I54: 19479 | J54: 2024 | K54: 10 | L54: =+IF(J54=0," ",K54-($B$9-J54)) -> 8 | M54: PROPIO | N54: BUENO | O54: CRÍTICO | P54: NO | R54: SI | S54: 2026 | T54: Interna | U54: Interna | X54: 2 | AA54: X | AG54: X
A55: Maternidad | B55: Hospital Regional Coyhaique | C55: apoyo terapeutico | D55: alto costo | E55: Incubadora Intensivo | F55: Draeger | G55: Isolette 8000 | H55: BB02215 | I55: 0286-12 | J55: 2012 | K55: 10 | L55: =+IF(J55=0," ",K55-($B$9-J55)) -> -4 | M55: PROPIO | N55: MALO | O55: CRÍTICO | P55: NO | R55: SI | S55: 2026 | T55: EXTERNO | U55: Draeger (P) | X55: 2 | AD55: X | AJ55: X
A56: Maternidad / PM | B56: Hospital Regional Coyhaique | C56: apoyo terapeutico | D56: alto costo | E56: Incubadora Intensivo | F56: Draeger | G56: Isolette 8000 | H56: BB02216 | I56: 0287-12 | J56: 2012 | K56: 10 | L56: =+IF(J56=0," ",K56-($B$9-J56)) -> -4 | M56: PROPIO | N56: MALO | O56: CRÍTICO | P56: NO | R56: SI | S56: 2026 | T56: EXTERNO | U56: Draeger (P) | X56: 2 | AD56: X | AJ56: X
A57: Ucin Neonatologia | B57: Hospital Regional Coyhaique | C57: apoyo terapeutico | D57: alto costo | E57: Incubadora Intensivo | F57: Draeger | G57: Caleo | H57: ASFL-0016 | I57: 0489-16 | J57: 2016 | K57: 10 | L57: =+IF(J57=0," ",K57-($B$9-J57)) -> 0 | M57: PROPIO | N57: MALO | O57: CRÍTICO | P57: NO | R57: SI | S57: 2026 | T57: EXTERNO | U57: Draeger (P) | X57: 2 | AD57: X | AJ57: X
A58: Ucin Neonatologia | B58: Hospital Regional Coyhaique | C58: apoyo terapeutico | D58: alto costo | E58: Incubadora Intensivo | F58: Draeger | G58: Isolette 8000 | H58: KF06236 | I58: 0490-16 | J58: 2016 | K58: 10 | L58: =+IF(J58=0," ",K58-($B$9-J58)) -> 0 | M58: PROPIO | N58: MALO | O58: CRÍTICO | P58: NO | R58: SI | S58: 2026 | T58: EXTERNO | U58: Draeger (P) | X58: 2 | AD58: X | AJ58: X
A59: Ucin Neonatologia | B59: Hospital Regional Coyhaique | C59: apoyo terapeutico | D59: alto costo | E59: Incubadora Intensivo | F59: Draeger | G59: Isolette 8000 | H59: KF06237 | I59: 0491-16 | J59: 2016 | K59: 10 | L59: =+IF(J59=0," ",K59-($B$9-J59)) -> 0 | M59: PROPIO | N59: MALO | O59: CRÍTICO | P59: NO | R59: SI | S59: 2026 | T59: EXTERNO | U59: Draeger (P) | X59: 2 | AD59: X | AJ59: X
A60: Ucin Neonatologia | B60: Hospital Regional Coyhaique | C60: apoyo terapeutico | D60: alto costo | E60: Incubadora de Transporte | F60: Draeger | G60: TI 500 | H60: KF10811 | I60: 0492-16 | J60: 2016 | K60: 10 | L60: =+IF(J60=0," ",K60-($B$9-J60)) -> 0 | M60: PROPIO | N60: MALO | O60: CRÍTICO | P60: NO | R60: SI | S60: 2026 | T60: EXTERNO | U60: Draeger (P) | X60: 2 | AD60: X | AJ60: X
A61: Pre-Parto | B61: Hospital Regional Coyhaique | C61: apoyo terapeutico | D61: alto costo | E61: Incubadora de Transporte | F61: Draeger | G61: TI 500 | H61: KF10797 | I61: 0493-16 | J61: 2016 | K61: 10 | L61: =+IF(J61=0," ",K61-($B$9-J61)) -> 0 | M61: PROPIO | N61: MALO | O61: CRÍTICO | P61: NO | R61: SI | S61: 2026 | T61: EXTERNO | U61: Draeger (P) | X61: 2 | AD61: X | AJ61: X
A62: Ucin Neonatologia | B62: Hospital Regional Coyhaique | C62: apoyo terapeutico | D62: alto costo | E62: Incubadora Intensivo | F62: General Electric | G62: Giraffe | H62: HDHV60044 | I62: 0563-16 | J62: 2016 | K62: 10 | L62: =+IF(J62=0," ",K62-($B$9-J62)) -> 0 | M62: PROPIO | N62: MALO | O62: CRÍTICO | P62: NO | R62: SI | S62: 2026 | T62: EXTERNO | U62: PV Equip (P) | X62: 2 | AD62: X | AJ62: X
A63: Urgencia Obstétrica | B63: Hospital Regional Coyhaique | C63: apoyo terapeutico | D63: alto costo | E63: Incubadora de Transporte | F63: Fanem | G63: IT-158-TS | H63: MAQ082090 | I63: 18066 | J63: 2020 | K63: 10 | L63: =+IF(J63=0," ",K63-($B$9-J63)) -> 4 | M63: PROPIO | N63: REGULAR | O63: CRÍTICO | P63: NO | R63: SI | S63: 2026 | T63: EXTERNO | U63: Hemisur (P) | X63: 2 | AA63: X | AG63: X
A64: Ucin Neonatologia | B64: Hospital Regional Coyhaique | C64: apoyo terapeutico | D64: alto costo | E64: Incubadora Intensivo | F64: Draeger | G64: Babyleo TN500 IncuWarmer | H64: ASRH-0013 | I64: 18796 | J64: 2023 | K64: 10 | L64: =+IF(J64=0," ",K64-($B$9-J64)) -> 7 | M64: PROPIO | N64: BUENO | O64: CRÍTICO | P64: NO | Q64: 20.01.26 | R64: SI | S64: 2026 | T64: EXTERNO | U64: Draeger (G) | X64: 2 | Y64: √ | AE64: X
A65: Ucin Neonatologia | B65: Hospital Regional Coyhaique | C65: apoyo terapeutico | D65: alto costo | E65: Incubadora Intensivo | F65: Draeger | G65: Babyleo TN500 IncuWarmer | H65: ASRH-0012 | I65: 18795 | J65: 2023 | K65: 10 | L65: =+IF(J65=0," ",K65-($B$9-J65)) -> 7 | M65: PROPIO | N65: BUENO | O65: CRÍTICO | P65: NO | Q65: 20.01.26 | R65: SI | S65: 2026 | T65: EXTERNO | U65: Draeger (G) | X65: 2 | Y65: √ | AE65: X
A66: Ucin Neonatologia | B66: Hospital Regional Coyhaique | C66: apoyo terapeutico | D66: alto costo | E66: Incubadora Intensivo | F66: Draeger | G66: Babyleo TN500 IncuWarmer | H66: ASRH-0011 | I66: 18794 | J66: 2023 | K66: 10 | L66: =+IF(J66=0," ",K66-($B$9-J66)) -> 7 | M66: PROPIO | N66: BUENO | O66: CRÍTICO | P66: NO | Q66: 20.01.26 | R66: SI | S66: 2026 | T66: EXTERNO | U66: Draeger (G) | X66: 2 | Y66: √ | AE66: X
A67: Ucin Neonatologia | B67: Hospital Regional Coyhaique | C67: apoyo terapeutico | D67: alto costo | E67: Incubadora Intensivo | F67: Draeger | G67: Babyleo TN500 IncuWarmer | H67: ASRH-0010 | I67: 18793 | J67: 2023 | K67: 10 | L67: =+IF(J67=0," ",K67-($B$9-J67)) -> 7 | M67: PROPIO | N67: BUENO | O67: CRÍTICO | P67: NO | Q67: 20.01.26 | R67: SI | S67: 2026 | T67: INTERNO | U67: Draeger (G) | X67: 2 | Y67: √ | AE67: X
A68: Ucin Neonatologia | B68: Hospital Regional Coyhaique | C68: apoyo terapeutico | D68: alto costo | E68: Incubadora Intensivo | F68: Draeger | G68: Babyleo TN500 IncuWarmer | H68: ASRH-0009 | I68: 18792 | J68: 2023 | K68: 10 | L68: =+IF(J68=0," ",K68-($B$9-J68)) -> 7 | M68: PROPIO | N68: BUENO | O68: CRÍTICO | P68: NO | Q68: 20.01.26 | R68: SI | S68: 2026 | T68: EXTERNO | U68: Draeger (G) | X68: 2 | Y68: √ | AE68: X
A69: Pre-Parto | B69: Hospital Regional Coyhaique | C69: apoyo terapeutico | D69: alto costo | E69: Incubadora de Transporte | F69: Fanem | G69: 158-TS | H69: FAT005912 | I69: 18985 | J69: 2023 | K69: 10 | L69: =+IF(J69=0," ",K69-($B$9-J69)) -> 7 | M69: PROPIO | N69: BUENO | O69: CRÍTICO | P69: SI | Q69: 17.05.26 | R69: SI | S69: 2026 | T69: EXTERNO | U69: Hemisur (G) | X69: 2 | AC69: X | AI69: X
A70: Pabellon quirurgico y anestesia | B70: Hospital Regional Coyhaique | C70: apoyo terapeutico | D70: alto costo | E70: Maquina de Anestesia | F70: Datex Ohmeda | G70: AESTIVA 3000 | H70: AMRD00972 | I70: 7030 | J70: 2007 | K70: 10 | L70: =+IF(J70=0," ",K70-($B$9-J70)) -> -9 | M70: PROPIO | N70: MALO | O70: CRÍTICO | P70: NO | R70: SI | S70: 2026 | T70: EXTERNO | U70: PV Equip (P) | X70: 2 | AD70: X | AJ70: X
A71: Pabellon quirurgico y anestesia | B71: Hospital Regional Coyhaique | C71: apoyo terapeutico | D71: alto costo | E71: Maquina de Anestesia | F71: General Electric | G71: AESPIRE VIEW | H71: APHS01466 | I71: 0082-13 | J71: 2013 | K71: 10 | L71: =+IF(J71=0," ",K71-($B$9-J71)) -> -3 | M71: PROPIO | N71: MALO | O71: CRÍTICO | P71: NO | R71: SI | S71: 2026 | T71: EXTERNO | U71: PV Equip (P) | X71: 2 | AD71: X | AJ71: X
A72: Pabellon quirurgico y anestesia | B72: Hospital Regional Coyhaique | C72: apoyo terapeutico | D72: alto costo | E72: Maquina de Anestesia | F72: General Electric | G72: AESPIRE VIEW | H72: APHS01468 | I72: 0083-13 | J72: 2013 | K72: 10 | L72: =+IF(J72=0," ",K72-($B$9-J72)) -> -3 | M72: PROPIO | N72: MALO | O72: CRÍTICO | P72: NO | R72: SI | S72: 2026 | T72: EXTERNO | U72: PV Equip (P) | X72: 2 | AD72: X | AJ72: X
A73: Pabellon quirurgico y anestesia | B73: Hospital Regional Coyhaique | C73: apoyo terapeutico | D73: alto costo | E73: Maquina de Anestesia | F73: General Electric | G73: AESPIRE VIEW | H73: APHS01467 | I73: 0084-13 | J73: 2013 | K73: 10 | L73: =+IF(J73=0," ",K73-($B$9-J73)) -> -3 | M73: PROPIO | N73: MALO | O73: CRÍTICO | P73: NO | R73: SI | S73: 2026 | T73: EXTERNO | U73: PV Equip (P) | X73: 2 | AD73: X | AJ73: X
A74: Pabellon quirurgico y anestesia | B74: Hospital Regional Coyhaique | C74: apoyo terapeutico | D74: alto costo | E74: Maquina de Anestesia | F74: General Electric | G74: Carestation 650 | H74: SM718460046MA | I74: 17368 | J74: 2018 | K74: 10 | L74: =+IF(J74=0," ",K74-($B$9-J74)) -> 2 | M74: PROPIO | N74: MALO | O74: CRÍTICO | P74: NO | R74: SI | S74: 2026 | T74: EXTERNO | U74: PV Equip (P) | X74: 2 | AD74: X | AJ74: X
A75: Pabellon quirurgico y anestesia | B75: Hospital Regional Coyhaique | C75: apoyo terapeutico | D75: alto costo | E75: Maquina de Anestesia | F75: General Electric | G75: Carestation 650 | H75: SM718460045MA | I75: 17370 | J75: 2018 | K75: 10 | L75: =+IF(J75=0," ",K75-($B$9-J75)) -> 2 | M75: PROPIO | N75: MALO | O75: CRÍTICO | P75: NO | R75: SI | S75: 2026 | T75: EXTERNO | U75: PV Equip (P) | X75: 2 | AD75: X | AJ75: X
A76: Imagenología (Resonancia Magnetica) | B76: Hospital Regional Coyhaique | C76: monitoreo | D76: alto costo | E76: Maquina de Anestesia | F76: Draeger | G76: Fabius GS MRI | H76: ASPH-0022 | I76: 18781 | J76: 2022 | K76: 10 | L76: =+IF(J76=0," ",K76-($B$9-J76)) -> 6 | M76: PROPIO | N76: BUENO | O76: CRÍTICO | P76: NO | Q76: 20.04.24 | R76: SI | S76: 2026 | T76: EXTERNO | U76: Draeger (G) | X76: 2 | AB76: X | AH76: X
A77: Uci adultos | B77: Hospital Regional Coyhaique | C77: apoyo terapeutico | D77: alto costo | E77: Ventilador de Transporte | F77: Carefusion | G77: LTV1200 | H77: E44479 | I77: 0047-10 | J77: 2010 | K77: 10 | L77: =+IF(J77=0," ",K77-($B$9-J77)) -> -6 | M77: PROPIO | N77: MALO | O77: CRÍTICO | P77: NO | R77: SI | S77: 2026 | T77: EXTERNO | U77: Hemisur (P) | X77: 2 | AD77: X | AJ77: X
A78: Uci adultos | B78: Hospital Regional Coyhaique | C78: apoyo terapeutico | D78: alto costo | E78: Ventilador Adulto No Invasivo | F78: Philips Respironics | G78: V60 | H78: 201002987 | I78: 0100-12 | J78: 2012 | K78: 10 | L78: =+IF(J78=0," ",K78-($B$9-J78)) -> -4 | M78: PROPIO | N78: MALO | O78: CRÍTICO | P78: NO | R78: SI | S78: 2026 | T78: EXTERNO | U78: Andover (P) | X78: 2 | AD78: X | AJ78: X
A79: Uci adultos | B79: Hospital Regional Coyhaique | C79: apoyo terapeutico | D79: alto costo | E79: Ventilador Adulto No Invasivo | F79: Philips Respironics | G79: V60 | H79: 100129782 | I79: 0537-16 | J79: 2016 | K79: 10 | L79: =+IF(J79=0," ",K79-($B$9-J79)) -> 0 | M79: PROPIO | N79: MALO | O79: CRÍTICO | P79: NO | R79: SI | S79: 2026 | T79: EXTERNO | U79: Andover (P) | X79: 2 | AD79: X | AJ79: X
A80: UTI pediatrica | B80: Hospital Regional Coyhaique | C80: apoyo terapeutico | D80: alto costo | E80: Ventilador Pediátrico No Invasivo | F80: Philips Respironics | G80: Trilogy 202 | H80: TV015091007 | I80: 0714-16 | J80: 2016 | K80: 10 | L80: =+IF(J80=0," ",K80-($B$9-J80)) -> 0 | M80: PROPIO | N80: MALO | O80: CRÍTICO | P80: NO | R80: SI | S80: 2026 | T80: EXTERNO | U80: Andover (P) | X80: 2 | AD80: X | AJ80: X
A81: UTI pediatrica | B81: Hospital Regional Coyhaique | C81: apoyo terapeutico | D81: alto costo | E81: Ventilador Pediátrico No Invasivo | F81: Philips Respironics | G81: Trilogy 202 | H81: TV016011310 | I81: 0715-16 | J81: 2016 | K81: 10 | L81: =+IF(J81=0," ",K81-($B$9-J81)) -> 0 | M81: PROPIO | N81: MALO | O81: CRÍTICO | P81: NO | R81: SI | S81: 2026 | T81: EXTERNO | U81: Andover (P) | X81: 2 | AD81: X | AJ81: X
A82: UTI pediatrica | B82: Hospital Regional Coyhaique | C82: apoyo terapeutico | D82: alto costo | E82: Ventilador Pediátrico No Invasivo | F82: Philips Respironics | G82: Trilogy 202 | H82: TV01601130F | I82: 0716-16 | J82: 2016 | K82: 10 | L82: =+IF(J82=0," ",K82-($B$9-J82)) -> 0 | M82: PROPIO | N82: MALO | O82: CRÍTICO | P82: NO | R82: SI | S82: 2026 | T82: EXTERNO | U82: Andover (P) | X82: 2 | AD82: X | AJ82: X
A83: UTI pediatrica | B83: Hospital Regional Coyhaique | C83: apoyo terapeutico | D83: alto costo | E83: Ventilador Pediátrico | F83: Maquett | G83: Servo-i | H83: 87167 | I83: 13482 | K83: 10 | L83: =+IF(J83=0," ",K83-($B$9-J83)) | M83: PROPIO | O83: CRÍTICO | P83: NO | R83: SI | S83: 2026 | T83: EXTERNO | U83: Andover (P) | X83: 2 | AD83: X | AJ83: X
A84: Ucin Neonatologia | B84: Hospital Regional Coyhaique | C84: apoyo terapeutico | D84: alto costo | E84: Ventilador Alta Frecuencia | F84: Draeger | G84: Babylog VN500 | H84: ASMD-0026 | I84: 17556 | J84: 2018 | K84: 10 | L84: =+IF(J84=0," ",K84-($B$9-J84)) -> 2 | M84: PROPIO | N84: MALO | O84: CRÍTICO | P84: NO | R84: SI | S84: 2026 | T84: EXTERNO | U84: Draeger (P) | X84: 2 | AD84: X | AJ84: X
A85: Ucin Neonatologia | B85: Hospital Regional Coyhaique | C85: apoyo terapeutico | D85: alto costo | E85: Ventilador Alta Frecuencia | F85: Draeger | G85: Babylog VN500 | H85: ASMD-0027 | I85: 17557 | J85: 2018 | K85: 10 | L85: =+IF(J85=0," ",K85-($B$9-J85)) -> 2 | M85: PROPIO | N85: REGULAR | O85: CRÍTICO | P85: NO | R85: SI | S85: 2026 | T85: EXTERNO | U85: Draeger (P) | X85: 2 | AD85: X | AJ85: X
A86: Ucin Neonatologia | B86: Hospital Regional Coyhaique | C86: apoyo terapeutico | D86: alto costo | E86: Ventilador Alta Frecuencia | F86: Draeger | G86: Babylog VN500 | H86: ASND-0047 | I86: 18016 | J86: 2020 | K86: 10 | L86: =+IF(J86=0," ",K86-($B$9-J86)) -> 4 | M86: PROPIO | N86: REGULAR | O86: CRÍTICO | P86: NO | Q86: 27.05.22 | R86: SI | S86: 2026 | T86: EXTERNO | U86: Draeger (P) | X86: 2 | AD86: X | AJ86: X
A87: Uci Adultos / Paciente Domicilio Lago Verde | B87: Hospital Regional Coyhaique | C87: apoyo terapeutico | D87: alto costo | E87: Ventilador de Transporte | F87: Newport | G87: HT70 Plus | H87: HT7P200173 | I87: 18036 | J87: 2020 | K87: 10 | L87: =+IF(J87=0," ",K87-($B$9-J87)) -> 4 | M87: PROPIO | N87: REGULAR | O87: CRÍTICO | P87: NO | Q87: 15.06.22 | R87: SI | S87: 2026 | T87: EXTERNO | U87: Medtronic(P) | X87: 2 | AD87: X | AJ87: X
A88: Urgencia | B88: Hospital Regional Coyhaique | C88: apoyo terapeutico | D88: alto costo | E88: Ventilador de Transporte | F88: Newport | G88: HT70 Plus | H88: HT7P200166 | I88: 18037 | J88: 2020 | K88: 10 | L88: =+IF(J88=0," ",K88-($B$9-J88)) -> 4 | M88: PROPIO | N88: REGULAR | O88: CRÍTICO | P88: NO | Q88: 15.06.22 | R88: SI | S88: 2026 | T88: EXTERNO | U88: Medtronic(P) | X88: 2 | AD88: X | AJ88: X
A89: Uci adultos / Bodega | B89: Hospital Regional Coyhaique | C89: apoyo terapeutico | D89: alto costo | E89: Ventilador Adulto | F89: MEK | G89: MV2000 | H89: MV2000TA2F0640 | I89: 18161 | J89: 2020 | K89: 10 | L89: =+IF(J89=0," ",K89-($B$9-J89)) -> 4 | M89: PROPIO | N89: REGULAR | O89: CRÍTICO | P89: NO | Q89: 21.08.21 | R89: SI | S89: 2026 | T89: EXTERNO | U89: Hemisur (P) | X89: 2 | AA89: X | AG89: X
A90: Uci adultos / Bodega | B90: Hospital Regional Coyhaique | C90: apoyo terapeutico | D90: alto costo | E90: Ventilador Adulto | F90: MEK | G90: MV2000 | H90: MV2000TA2F0627 | I90: 18162 | J90: 2020 | K90: 10 | L90: =+IF(J90=0," ",K90-($B$9-J90)) -> 4 | M90: PROPIO | N90: REGULAR | O90: CRÍTICO | P90: NO | Q90: 21.08.21 | R90: SI | S90: 2026 | T90: EXTERNO | U90: Hemisur (P) | X90: 2 | AA90: X | AG90: X
A91: Uci adultos / Bodega | B91: Hospital Regional Coyhaique | C91: apoyo terapeutico | D91: alto costo | E91: Ventilador Adulto | F91: MEK | G91: MV2000 | H91: MV2000TA2F0742 | I91: 18163 | J91: 2020 | K91: 10 | L91: =+IF(J91=0," ",K91-($B$9-J91)) -> 4 | M91: PROPIO | N91: REGULAR | O91: CRÍTICO | P91: NO | Q91: 21.08.21 | R91: SI | S91: 2026 | T91: EXTERNO | U91: Hemisur (P) | X91: 2 | AA91: X | AG91: X
A92: Uci adultos / PM | B92: Hospital Regional Coyhaique | C92: apoyo terapeutico | D92: alto costo | E92: Ventilador Adulto | F92: MEK | G92: MV2000 | H92: MV2000TA2F0629 | I92: 18164 | J92: 2020 | K92: 10 | L92: =+IF(J92=0," ",K92-($B$9-J92)) -> 4 | M92: PROPIO | N92: REGULAR | O92: CRÍTICO | P92: NO | Q92: 21.08.21 | R92: SI | S92: 2026 | T92: EXTERNO | U92: Hemisur (P) | X92: 2 | AA92: X | AG92: X
A93: Uci adultos / Bodega | B93: Hospital Regional Coyhaique | C93: apoyo terapeutico | D93: alto costo | E93: Ventilador Adulto | F93: MEK | G93: MV2000 | H93: MV2000TA2F0746 | I93: 18165 | J93: 2020 | K93: 10 | L93: =+IF(J93=0," ",K93-($B$9-J93)) -> 4 | M93: PROPIO | N93: REGULAR | O93: CRÍTICO | P93: NO | Q93: 21.08.21 | R93: SI | S93: 2026 | T93: EXTERNO | U93: Hemisur (P) | X93: 2 | AA93: X | AG93: X
A94: Uci adultos / Urgencia | B94: Hospital Regional Coyhaique | C94: apoyo terapeutico | D94: alto costo | E94: Ventilador Adulto | F94: MEK | G94: MV2000 | H94: MV2000TA2F0733 | I94: 18166 | J94: 2020 | K94: 10 | L94: =+IF(J94=0," ",K94-($B$9-J94)) -> 4 | M94: PROPIO | N94: REGULAR | O94: CRÍTICO | P94: NO | Q94: 21.08.21 | R94: SI | S94: 2026 | T94: EXTERNO | U94: Hemisur (P) | X94: 2 | AA94: X | AG94: X
A95: Uci adultos / PM | B95: Hospital Regional Coyhaique | C95: apoyo terapeutico | D95: alto costo | E95: Ventilador Adulto | F95: MEK | G95: MV2000 | H95: MV2000TA2F0737 | I95: 18167 | J95: 2020 | K95: 10 | L95: =+IF(J95=0," ",K95-($B$9-J95)) -> 4 | M95: PROPIO | N95: REGULAR | O95: CRÍTICO | P95: NO | Q95: 21.08.21 | R95: SI | S95: 2026 | T95: EXTERNO | U95: Hemisur (P) | X95: 2 | AA95: X | AG95: X
A96: Uci adultos / Bodega | B96: Hospital Regional Coyhaique | C96: apoyo terapeutico | D96: alto costo | E96: Ventilador Adulto | F96: MEK | G96: MV2000 | H96: MV2000TA2F0739 | I96: 18168 | J96: 2020 | K96: 10 | L96: =+IF(J96=0," ",K96-($B$9-J96)) -> 4 | M96: PROPIO | N96: REGULAR | O96: CRÍTICO | P96: NO | Q96: 21.08.21 | R96: SI | S96: 2026 | T96: EXTERNO | U96: Hemisur (P) | X96: 2 | AA96: X | AG96: X
A97: Uci adultos / Bodega | B97: Hospital Regional Coyhaique | C97: apoyo terapeutico | D97: alto costo | E97: Ventilador Adulto | F97: MEK | G97: MV2000 | H97: MV2000TA2F0743 | I97: 18169 | J97: 2020 | K97: 10 | L97: =+IF(J97=0," ",K97-($B$9-J97)) -> 4 | M97: PROPIO | N97: REGULAR | O97: CRÍTICO | P97: NO | Q97: 21.08.21 | R97: SI | S97: 2026 | T97: EXTERNO | U97: Hemisur (P) | X97: 2 | AA97: X | AG97: X
A98: Uci adultos | B98: Hospital Regional Coyhaique | C98: apoyo terapeutico | D98: alto costo | E98: Ventilador Adulto | F98: Puritan Bennett | G98: PB 840 | H98: 3512202071 | I98: 18187 | J98: 2020 | K98: 10 | L98: =+IF(J98=0," ",K98-($B$9-J98)) -> 4 | M98: PROPIO | N98: REGULAR | O98: CRÍTICO | P98: NO | Q98: 16.10.22 | R98: SI | S98: 2026 | T98: EXTERNO | U98: Medtronic(P) | X98: 2 | AD98: X | AJ98: X
A99: Uci adultos | B99: Hospital Regional Coyhaique | C99: apoyo terapeutico | D99: alto costo | E99: Ventilador Adulto | F99: Puritan Bennett | G99: PB 840 | H99: 3512202255 | I99: 18188 | J99: 2020 | K99: 10 | L99: =+IF(J99=0," ",K99-($B$9-J99)) -> 4 | M99: PROPIO | N99: REGULAR | O99: CRÍTICO | P99: NO | Q99: 16.10.22 | R99: SI | S99: 2026 | T99: EXTERNO | U99: Medtronic(P) | X99: 2 | AD99: X | AJ99: X
A100: Uci adultos | B100: Hospital Regional Coyhaique | C100: apoyo terapeutico | D100: alto costo | E100: Ventilador Adulto | F100: Puritan Bennett | G100: PB 980 | H100: 35B2004411 | I100: 18189 | J100: 2020 | K100: 10 | L100: =+IF(J100=0," ",K100-($B$9-J100)) -> 4 | M100: PROPIO | N100: REGULAR | O100: CRÍTICO | P100: NO | Q100: 16.10.22 | R100: SI | S100: 2026 | T100: EXTERNO | U100: Medtronic(P) | X100: 2 | AD100: X | AJ100: X
A101: Uci adultos | B101: Hospital Regional Coyhaique | C101: apoyo terapeutico | D101: alto costo | E101: Ventilador Adulto | F101: Puritan Bennett | G101: PB 980 | H101: 35B2004243 | I101: 18190 | J101: 2020 | K101: 10 | L101: =+IF(J101=0," ",K101-($B$9-J101)) -> 4 | M101: PROPIO | N101: REGULAR | O101: CRÍTICO | P101: NO | Q101: 16.10.22 | R101: SI | S101: 2026 | T101: EXTERNO | U101: Medtronic(P) | X101: 2 | AD101: X | AJ101: X
A102: Uci adultos | B102: Hospital Regional Coyhaique | C102: apoyo terapeutico | D102: alto costo | E102: Ventilador Adulto | F102: Maquet | G102: Servo-i | H102: 100565 | I102: 18197 | J102: 2020 | K102: 10 | L102: =+IF(J102=0," ",K102-($B$9-J102)) -> 4 | M102: PROPIO | N102: REGULAR | O102: CRÍTICO | P102: NO | Q102: 28.10.21 | R102: SI | S102: 2026 | T102: EXTERNO | U102: Andover (C) | X102: 2 | AB102: X | AH102: X
A103: Uci adultos | B103: Hospital Regional Coyhaique | C103: apoyo terapeutico | D103: alto costo | E103: Ventilador Adulto | F103: Maquet | G103: Servo-i | H103: 100566 | I103: 18198 | J103: 2020 | K103: 10 | L103: =+IF(J103=0," ",K103-($B$9-J103)) -> 4 | M103: PROPIO | N103: REGULAR | O103: CRÍTICO | P103: NO | Q103: 28.10.21 | R103: SI | S103: 2026 | T103: EXTERNO | U103: Andover (C) | X103: 2 | AB103: X | AH103: X
A104: Uci adultos | B104: Hospital Regional Coyhaique | C104: apoyo terapeutico | D104: alto costo | E104: Ventilador Adulto | F104: Maquet | G104: Servo-i | H104: 100567 | I104: 18199 | J104: 2020 | K104: 10 | L104: =+IF(J104=0," ",K104-($B$9-J104)) -> 4 | M104: PROPIO | N104: REGULAR | O104: CRÍTICO | P104: NO | Q104: 28.10.21 | R104: SI | S104: 2026 | T104: EXTERNO | U104: Andover (C) | X104: 2 | AB104: X | AH104: X
A105: Uci adultos | B105: Hospital Regional Coyhaique | C105: apoyo terapeutico | D105: alto costo | E105: Ventilador Adulto | F105: Maquet | G105: Servo-i | H105: 100568 | I105: 18200 | J105: 2020 | K105: 10 | L105: =+IF(J105=0," ",K105-($B$9-J105)) -> 4 | M105: PROPIO | N105: REGULAR | O105: CRÍTICO | P105: NO | Q105: 28.10.21 | R105: SI | S105: 2026 | T105: EXTERNO | U105: Andover (C) | X105: 2 | AB105: X | AH105: X
...

Sheet SEGUIMIENTO GASTO
B3: SEGUIMIENTO GASTO CONVENIOS DE MANTENIMIENTO
K5: CONTROL MENSUAL EJECUCIÓN
K6: ENERO | M6: FEBRERO | O6: MARZO | Q6: ABRIL | S6: MAYO | U6: JUNIO | W6: JULIO | Y6: AGOSTO | AA6: SEPTIEMBRE | AC6: OCTUBRE | AE6: NOVIEMBRE | AG6: DICIEMBRE
B7: Nº | C7: SERVICIO DE SALUD | D7: ESTABLECIMIENTO | E7: NOMBRE CONVENIO DE MANTENIMIENTO | F7: Nº RESOLUCIÓN / ID / ORDEN DE COMPRA DEL CONVENIO | G7: FECHA RESOLUCIÓN | H7: FECHA DE EXPIRACION CONVENIO | I7: MONTO ANUAL ($) | J7: SUBASIGNACIÓN SIGFE | K7: N° ORDEN DE COMPRA / N° FACTURA | L7: MONTO ($) | M7: N° ORDEN DE COMPRA / N° FACTURA | N7: MONTO ($) | O7: N° ORDEN DE COMPRA / N° FACTURA | P7: MONTO ($) | Q7: N° ORDEN DE COMPRA / N° FACTURA | R7: MONTO ($) | S7: N° ORDEN DE COMPRA / N° FACTURA | T7: MONTO ($) | U7: N° ORDEN DE COMPRA / N° FACTURA | V7: MONTO ($) | W7: N° ORDEN DE COMPRA / N° FACTURA | X7: MONTO ($) | Y7: N° ORDEN DE COMPRA / N° FACTURA | Z7: MONTO ($) | AA7: N° ORDEN DE COMPRA / N° FACTURA | AB7: MONTO ($) | AC7: N° ORDEN DE COMPRA / N° FACTURA | AD7: MONTO ($) | AE7: N° ORDEN DE COMPRA / N° FACTURA | AF7: MONTO ($) | AG7: N° ORDEN DE COMPRA / N° FACTURA | AH7: MONTO ($) | AI7: TOTAL
B8: 1 | C8: AYSEN | D8: Hospital Regional Coyhaique | E8: ORDENES 2025 SIN PAGO, ESPERANDO REGULARIZACION PRESUPUESTO 2026 | J8: 22.06.006.003 | L8: 0 | N8: 0 | P8: 0 | R8: 0 | T8: 0 | V8: 0 | X8: 0 | Z8: 0 | AB8: 0 | AD8: 0 | AF8: 0 | AH8: 0 | AI8: =+L8+N8+P8+R8+T8+V8+X8+Z8+AB8+AD8+AF8+AH8 -> 0
B9: 2 | C9: AYSEN | D9: Hospital Regional Coyhaique | E9: CONVENIO ANDOVER RES 10016 Y 14499 | F9: 1366597-2998-TD25 | G9: 45142 | H9: 46238 | I9: 4329719 | J9: 22.06.006.003 | L9: 0 | N9: 0 | P9: 0 | R9: 0 | T9: 0 | V9: 0 | X9: 0 | Z9: 0 | AB9: 0 | AD9: 0 | AF9: 0 | AH9: 0 | AI9: =+L9+N9+P9+R9+T9+V9+X9+Z9+AB9+AD9+AF9+AH9 -> 0
B10: 3 | C10: AYSEN | D10: Hospital Regional Coyhaique | F10: 1366597-3463-TD25 | I10: 4329719 | J10: 22.06.006.003 | L10: 0 | M10: 1366597-3463-TD25 | N10: 4329719 | P10: 0 | R10: 0 | T10: 0 | V10: 0 | X10: 0 | Z10: 0 | AB10: 0 | AD10: 0 | AF10: 0 | AH10: 0 | AI10: =+L10+N10+P10+R10+T10+V10+X10+Z10+AB10+AD10+AF10+AH10 -> 4329719
B11: 4 | C11: AYSEN | D11: Hospital Regional Coyhaique | F11: 1366597-3692-TD25 | I11: 4329719 | J11: 22.06.006.003 | M11: 1366597-3692-TD25 | N11: 4329719 | P11: 0 | R11: 0 | T11: 0 | V11: 0 | X11: 0 | Z11: 0 | AB11: 0 | AD11: 0 | AF11: 0 | AH11: 0 | AI11: =+L11+N11+P11+R11+T11+V11+X11+Z11+AB11+AD11+AF11+AH11 -> 4329719
B12: 5 | C12: AYSEN | D12: Hospital Regional Coyhaique | F12: 1366597-3999-TD25 | I12: 4329719 | J12: 22.06.006.003 | L12: 0 | M12: 1366597-3999-TD25 | N12: 4329719 | P12: 0 | R12: 0 | T12: 0 | V12: 0 | X12: 0 | Z12: 0 | AB12: 0 | AD12: 0 | AF12: 0 | AH12: 0 | AI12: =+L12+N12+P12+R12+T12+V12+X12+Z12+AB12+AD12+AF12+AH12 -> 4329719
B13: 6 | C13: AYSEN | D13: Hospital Regional Coyhaique | E13: CONVENIO PHILIPS EQUIPO DE RAYOS RES 10851 PAGADO CON PRESUPUESTO 2026 | F13: 1366597-4052-TD25 | G13: 45843 | H13: 46208 | I13: 14077700 | J13: 22.06.006.003 | K13: 1366597-4052-TD25 | L13: 14077700 | N13: 0 | P13: 0 | R13: 0 | T13: 0 | V13: 0 | X13: 0 | Z13: 0 | AB13: 0 | AD13: 0 | AF13: 0 | AH13: 0 | AI13: =+L13+N13+P13+R13+T13+V13+X13+Z13+AB13+AD13+AF13+AH13 -> 14077700
B14: 7 | C14: AYSEN | D14: Hospital Regional Coyhaique | F14: 1366597-4054-TD25 | I14: 14077700 | J14: 22.06.006.003 | K14: 1366597-4054-TD25 | L14: 14077700 | N14: 0 | P14: 0 | R14: 0 | T14: 0 | V14: 0 | X14: 0 | Z14: 0 | AB14: 0 | AD14: 0 | AF14: 0 | AH14: 0 | AI14: =+L14+N14+P14+R14+T14+V14+X14+Z14+AB14+AD14+AF14+AH14 -> 14077700
B15: 8 | C15: AYSEN | D15: Hospital Regional Coyhaique | F15: 1366597-4055-TD25 | I15: 14077700 | J15: 22.06.006.003 | K15: 1366597-4055-TD25 | L15: 14077700 | N15: 0 | P15: 0 | R15: 0 | T15: 0 | V15: 0 | X15: 0 | Z15: 0 | AB15: 0 | AD15: 0 | AF15: 0 | AH15: 0 | AI15: =+L15+N15+P15+R15+T15+V15+X15+Z15+AB15+AD15+AF15+AH15 -> 14077700
B16: 9 | C16: AYSEN | D16: Hospital Regional Coyhaique | F16: 1366597-4056-TD25 | I16: 14077700 | J16: 22.06.006.003 | K16: 1366597-4056-TD25 | L16: 14077700 | N16: 0 | P16: 0 | R16: 0 | T16: 0 | V16: 0 | X16: 0 | Z16: 0 | AB16: 0 | AD16: 0 | AF16: 0 | AH16: 0 | AI16: =+L16+N16+P16+R16+T16+V16+X16+Z16+AB16+AD16+AF16+AH16 -> 14077700
B17: 10 | C17: AYSEN | D17: Hospital Regional Coyhaique | E17: CONVENIO AGFA 6346 | F17: 1366597-2225-TD25 | G17: 45413 | H17: 46142 | I17: 877587 | J17: 22.06.006.003 | L17: 0 | N17: 0 | P17: 0 | R17: 0 | T17: 0 | V17: 0 | X17: 0 | Z17: 0 | AB17: 0 | AD17: 0 | AF17: 0 | AH17: 0 | AI17: =+L17+N17+P17+R17+T17+V17+X17+Z17+AB17+AD17+AF17+AH17 -> 0
B18: 11 | C18: AYSEN | D18: Hospital Regional Coyhaique | F18: 1366597-2995-TD25 | I18: 877587 | J18: 22.06.006.003 | L18: 0 | N18: 0 | P18: 0 | R18: 0 | T18: 0 | V18: 0 | X18: 0 | Z18: 0 | AB18: 0 | AD18: 0 | AF18: 0 | AH18: 0 | AI18: =+L18+N18+P18+R18+T18+V18+X18+Z18+AB18+AD18+AF18+AH18 -> 0
B19: 12 | C19: AYSEN | D19: Hospital Regional Coyhaique | F19: 1366597-3338-TD25 | I19: 877587 | J19: 22.06.006.003 | K19: 1366597-3338-TD25 | L19: 877587 | N19: 0 | P19: 0 | R19: 0 | T19: 0 | V19: 0 | X19: 0 | Z19: 0 | AB19: 0 | AD19: 0 | AF19: 0 | AH19: 0 | AI19: =+L19+N19+P19+R19+T19+V19+X19+Z19+AB19+AD19+AF19+AH19 -> 877587
B20: 13 | C20: AYSEN | D20: Hospital Regional Coyhaique | F20: 1366597-3691-TD25 | I20: 877587 | J20: 22.06.006.003 | K20: 1366597-3691-TD25 | L20: 877587 | N20: 0 | P20: 0 | R20: 0 | T20: 0 | V20: 0 | X20: 0 | Z20: 0 | AB20: 0 | AD20: 0 | AF20: 0 | AH20: 0 | AI20: =+L20+N20+P20+R20+T20+V20+X20+Z20+AB20+AD20+AF20+AH20 -> 877587
B21: 14 | C21: AYSEN | D21: Hospital Regional Coyhaique | F21: 1366597-3994-TD25 | I21: 877587 | J21: 22.06.006.003 | L21: 0 | N21: 0 | P21: 0 | R21: 0 | T21: 0 | V21: 0 | X21: 0 | Z21: 0 | AB21: 0 | AD21: 0 | AF21: 0 | AH21: 0 | AI21: =+L21+N21+P21+R21+T21+V21+X21+Z21+AB21+AD21+AF21+AH21 -> 0
B22: 15 | C22: AYSEN | D22: Hospital Regional Coyhaique | E22: CONVENIO RESONADOR 16341 PAGADO CON PRESUPUESTO 2026 | F22: 1366597-3666-TD25 | G22: 45931 | H22: 46296 | I22: 10259287 | J22: 22.06.006.003 | K22: 1366597-3666-TD25 | L22: 10259287 | N22: 0 | P22: 0 | R22: 0 | T22: 0 | V22: 0 | X22: 0 | Z22: 0 | AB22: 0 | AD22: 0 | AF22: 0 | AH22: 0 | AI22: =+L22+N22+P22+R22+T22+V22+X22+Z22+AB22+AD22+AF22+AH22 -> 10259287
B23: 16 | C23: AYSEN | D23: Hospital Regional Coyhaique | F23: 1366597-4003-TD25 | I23: 10259287 | J23: 22.06.006.003 | K23: 1366597-4003-TD25 | L23: 10259287 | N23: 0 | P23: 0 | R23: 0 | T23: 0 | V23: 0 | X23: 0 | Z23: 0 | AB23: 0 | AD23: 0 | AF23: 0 | AH23: 0 | AI23: =+L23+N23+P23+R23+T23+V23+X23+Z23+AB23+AD23+AF23+AH23 -> 10259287
B24: 17 | H24: deuda en convenios 2025 | I24: =I9+I10+I11+I12+I17+I18+I19+I20+I21 -> 21706811
B25: 18 | C25: AYSEN | D25: Hospital Regional Coyhaique | E25: ORDENES 2025 SIN PAGO, ESPERANDO REGULARIZACION PRESUPUESTO 2026 | I25: 0 | J25: 22.06.006.003 | L25: 0 | N25: 0 | P25: 0 | R25: 0 | T25: 0 | V25: 0 | X25: 0 | Z25: 0 | AB25: 0 | AD25: 0 | AF25: 0 | AH25: 0 | AI25: =+L25+N25+P25+R25+T25+V25+X25+Z25+AB25+AD25+AF25+AH25 -> 0
B26: 19 | C26: AYSEN | D26: Hospital Regional Coyhaique | E26: MANTENCION PREVENTIVA BBRAUN FINALIZADA CON ERROR EN EL DEVENGO | F26: 4778-312-TD25 | I26: 1748983 | J26: 22.06.006.003 | L26: 0 | N26: 0 | P26: 0 | R26: 0 | T26: 0 | V26: 0 | X26: 0 | Z26: 0 | AB26: 0 | AD26: 0 | AF26: 0 | AH26: 0 | AI26: =+L26+N26+P26+R26+T26+V26+X26+Z26+AB26+AD26+AF26+AH26 -> 0
B27: 20 | C27: AYSEN | D27: Hospital Regional Coyhaique | E27: MANTENCION PREVENTIVA ROCHEM FINALIZADA CON ERROR EN EL DEVENGO | F27: 4778-350-TD25 | I27: 2023000 | J27: 22.06.006.003 | L27: 0 | N27: 0 | P27: 0 | R27: 0 | T27: 0 | V27: 0 | X27: 0 | Z27: 0 | AB27: 0 | AD27: 0 | AF27: 0 | AH27: 0 | AI27: =+L27+N27+P27+R27+T27+V27+X27+Z27+AB27+AD27+AF27+AH27 -> 0
B28: 21 | C28: AYSEN | D28: Hospital Regional Coyhaique | E28: MANTENCION PREVENTIVA MEDPLAN FINALIZADA CON ERROR EN EL DEVENGO | F28: 4778-409-TD25 | I28: 1068620 | J28: 22.06.006.003 | L28: 0 | N28: 0 | P28: 0 | R28: 0 | T28: 0 | V28: 0 | X28: 0 | Z28: 0 | AB28: 0 | AD28: 0 | AF28: 0 | AH28: 0 | AI28: =+L28+N28+P28+R28+T28+V28+X28+Z28+AB28+AD28+AF28+AH28 -> 0
B29: 22 | C29: AYSEN | D29: Hospital Regional Coyhaique | E29: MANTENCION PREVENTIVA BIOMERIUX FINALIZADA CON ERROR EN EL DEVENGO | F29: 4778-441-TD25 | I29: 4485762 | J29: 22.06.006.003 | L29: 0 | N29: 0 | P29: 0 | R29: 0 | T29: 0 | V29: 0 | X29: 0 | Z29: 0 | AB29: 0 | AD29: 0 | AF29: 0 | AH29: 0 | AI29: =+L29+N29+P29+R29+T29+V29+X29+Z29+AB29+AD29+AF29+AH29 -> 0
B30: 23 | C30: AYSEN | D30: Hospital Regional Coyhaique | E30: MANTENCION PREVENTIVA DRAGER FINALIZADA CON ERROR EN EL DEVENGO | F30: 4778-439-TD25 | I30: 2210187 | J30: 22.06.006.003 | L30: 0 | N30: 0 | P30: 0 | R30: 0 | T30: 0 | V30: 0 | X30: 0 | Z30: 0 | AB30: 0 | AD30: 0 | AF30: 0 | AH30: 0 | AI30: =+L30+N30+P30+R30+T30+V30+X30+Z30+AB30+AD30+AF30+AH30 -> 0
B31: 25 | C31: AYSEN | D31: Hospital Regional Coyhaique | E31: MANTENCION PREVENTIVA TECNOIMAGEN FINALIZADA CON ERROR EN EL DEVENGO | F31: 4778-444-TD25 | I31: 5913907 | J31: 22.06.006.003 | L31: 0 | N31: 0 | P31: 0 | R31: 0 | T31: 0 | V31: 0 | X31: 0 | Z31: 0 | AB31: 0 | AD31: 0 | AF31: 0 | AH31: 0 | AI31: =+L31+N31+P31+R31+T31+V31+X31+Z31+AB31+AD31+AF31+AH31 -> 0
B32: 26 | C32: AYSEN | D32: Hospital Regional Coyhaique | E32: MANTENCION PREVENTIVA HEMIFERIO FINALIZADA CON ERROR EN EL DEVENGO | F32: 4778-469-TD25 | I32: 13435100 | J32: 22.06.006.003 | L32: 0 | N32: 0 | P32: 0 | R32: 0 | T32: 0 | V32: 0 | X32: 0 | Z32: 0 | AB32: 0 | AD32: 0 | AF32: 0 | AH32: 0 | AI32: =+L32+N32+P32+R32+T32+V32+X32+Z32+AB32+AD32+AF32+AH32 -> 0
B33: 27 | C33: AYSEN | D33: Hospital Regional Coyhaique | E33: MANTENCION PREVENTIVA FULLTECHNOLOGY FINALIZADA CON ERROR EN EL DEVENGO | F33: 4778-504-TD25 | I33: 4438700 | J33: 22.06.006.003 | L33: 0 | N33: 0 | P33: 0 | R33: 0 | T33: 0 | V33: 0 | X33: 0 | Z33: 0 | AB33: 0 | AD33: 0 | AF33: 0 | AH33: 0 | AI33: =+L33+N33+P33+R33+T33+V33+X33+Z33+AB33+AD33+AF33+AH33 -> 0
B34: 28 | C34: AYSEN | D34: Hospital Regional Coyhaique | E34: MANTENCION PREVENTIVA CENTRAL DE COMPRAS DEL EXTRASISTEMA S.A. FINALIZADA CON ERROR EN EL DEVENGO | F34: 4778-506-TD25 | I34: 4231640 | J34: 22.06.006.003 | L34: 0 | N34: 0 | P34: 0 | R34: 0 | T34: 0 | V34: 0 | X34: 0 | Z34: 0 | AB34: 0 | AD34: 0 | AF34: 0 | AH34: 0 | AI34: =+L34+N34+P34+R34+T34+V34+X34+Z34+AB34+AD34+AF34+AH34 -> 0
B35: 29 | C35: AYSEN | D35: Hospital Regional Coyhaique | E35: MANTENCION PREVENTIVA PV EQUIP FINALIZADA CON ERROR EN EL DEVENGO | F35: 4778-509-TD25 | I35: 24112369 | J35: 22.06.006.003 | L35: 0 | N35: 0 | P35: 0 | R35: 0 | T35: 0 | V35: 0 | X35: 0 | Z35: 0 | AB35: 0 | AD35: 0 | AF35: 0 | AH35: 0 | AI35: =+L35+N35+P35+R35+T35+V35+X35+Z35+AB35+AD35+AF35+AH35 -> 0
B36: 30 | C36: AYSEN | D36: Hospital Regional Coyhaique | E36: MANTENCION PREVENTIVA ASP FINALIZADA CON ERROR EN EL DEVENGO | F36: 4778-501-TD25 | I36: 5611255 | J36: 22.06.006.003 | L36: 0 | N36: 0 | P36: 0 | R36: 0 | T36: 0 | V36: 0 | X36: 0 | Z36: 0 | AB36: 0 | AD36: 0 | AF36: 0 | AH36: 0 | AI36: =+L36+N36+P36+R36+T36+V36+X36+Z36+AB36+AD36+AF36+AH36 -> 0
B37: 32 | C37: AYSEN | D37: Hospital Regional Coyhaique | E37: MANTENCION PREVENTIVA GRUPO BIOS FINALIZADA CON ERROR EN EL DEVENGO | F37: 4778-577-TD25 | I37: 1480658 | J37: 22.06.006.003 | L37: 0 | N37: 0 | P37: 0 | R37: 0 | T37: 0 | V37: 0 | X37: 0 | Z37: 0 | AB37: 0 | AD37: 0 | AF37: 0 | AH37: 0 | AI37: =+L37+N37+P37+R37+T37+V37+X37+Z37+AB37+AD37+AF37+AH37 -> 0
... B44: 39 | C44: AYSEN | D44: Hospital Regional Coyhaique | E44: MANTENCION PREVENTIVA GRUPO BIOS TODAVIA NO SE REALIZA LA MANTENCION SIN RC | F44: 4778-551-TD25 | I44: 1269135 | J44: 22.06.006.003 | L44: 0 | N44: 0 | P44: 0 | R44: 0 | T44: 0 | V44: 0 | X44: 0 | Z44: 0 | AB44: 0 | AD44: 0 | AF44: 0 | AH44: 0 | AI44: =+L44+N44+P44+R44+T44+V44+X44+Z44+AB44+AD44+AF44+AH44 -> 0
B45: 40 | C45: AYSEN | D45: Hospital Regional Coyhaique | E45: MANTENCION PREVENTIVA INGENIERIA E IMPORTACIONES M & M LTDA. DEVENGO MANUAL CON PRESUPUESTO 2026 | F45: 4778-532-TD25 | H45: 46034 | I45: 1416100 | J45: 22.06.006.003 | K45: 4778-532-TD25 | L45: 1416100 | N45: 0 | P45: 0 | R45: 0 | T45: 0 | V45: 0 | X45: 0 | Z45: 0 | AB45: 0 | AD45: 0 | AF45: 0 | AH45: 0 | AI45: =+L45+N45+P45+R45+T45+V45+X45+Z45+AB45+AD45+AF45+AH45 -> 1416100
B46: 41 | C46: AYSEN | D46: Hospital Regional Coyhaique | E46: MANTENCION PREVENTIVA PVEQUIP FINALIZADA CON ERROR EN EL DEVENGO | F46: 4778-557-TD25 | I46: 5057348 | J46: 22.06.006.003 | L46: 0 | N46: 0 | P46: 0 | R46: 0 | T46: 0 | V46: 0 | X46: 0 | Z46: 0 | AB46: 0 | AD46: 0 | AF46: 0 | AH46: 0 | AI46: =+L46+N46+P46+R46+T46+V46+X46+Z46+AB46+AD46+AF46+AH46 -> 0
B47: 42 | C47: AYSEN | D47: Hospital Regional Coyhaique | E47: MANTENCION PREVENTIVA MEDTRONIC FINALIZADA PROBLEMA RECEPCION CONFORME | F47: 4778-555-TD25 | I47: 7145236 | J47: 22.06.006.003 | L47: 0 | N47: 0 | P47: 0 | R47: 0 | T47: 0 | V47: 0 | X47: 0 | Z47: 0 | AB47: 0 | AD47: 0 | AF47: 0 | AH47: 0 | AI47: =+L47+N47+P47+R47+T47+V47+X47+Z47+AB47+AD47+AF47+AH47 -> 0
B48: 43 | C48: AYSEN | D48: Hospital Regional Coyhaique | E48: MANTENCION PREVENTIVA HEMIFERIO FINALIZADA CON ERROR EN EL DEVENGO | F48: 4778-582-TD25 | I48: 4046000 | J48: 22.06.006.003 | L48: 0 | N48: 0 | P48: 0 | R48: 0 | T48: 0 | V48: 0 | X48: 0 | Z48: 0 | AB48: 0 | AD48: 0 | AF48: 0 | AH48: 0 | AI48: =+L48+N48+P48+R48+T48+V48+X48+Z48+AB48+AD48+AF48+AH48 -> 0
B49: 44 | C49: AYSEN | D49: Hospital Regional Coyhaique | E49: MANTENCION PREVENTIVA ANDOVER FINALIZADA EL PROVEEDOR LE FALTA FACTURAR | F49: 4778-710-TD25 | I49: 1904873 | J49: 22.06.006.003 | K49: 4778-710-TD25 | L49: 1904873 | N49: 0 | P49: 0 | R49: 0 | T49: 0 | V49: 0 | X49: 0 | Z49: 0 | AB49: 0 | AD49: 0 | AF49: 0 | AH49: 0 | AI49: =+L49+N49+P49+R49+T49+V49+X49+Z49+AB49+AD49+AF49+AH49 -> 1904873
B50: 45 | C50: AYSEN | D50: Hospital Regional Coyhaique | E50: MANTENCION PREVENTIVA ARQUIMED SE DEBE REGULARIZAR ORDEN DE COMPRA AUTORIZADA | F50: 4778-681-TD25 | I50: 2068220 | J50: 22.06.006.003 | K50: 4778-681-TD25 | L50: 2068220 | N50: 0 | P50: 0 | R50: 0 | T50: 0 | V50: 0 | X50: 0 | Z50: 0 | AB50: 0 | AD50: 0 | AF50: 0 | AH50: 0 | AI50: =+L50+N50+P50+R50+T50+V50+X50+Z50+AB50+AD50+AF50+AH50 -> 2068220
B51: 46 | C51: AYSEN | D51: Hospital Regional Coyhaique | E51: MANTENCION PREVENTIVA BLUEMEDICAL SE DEBE REGULARIZAR ORDEN DE COMPRA AUTORIZADA | F51: 4778-673-TD25 | I51: 1785000 | J51: 22.06.006.003 | L51: 0 | N51: 0 | P51: 0 | R51: 0 | T51: 0 | V51: 0 | X51: 0 | Z51: 0 | AB51: 0 | AD51: 0 | AF51: 0 | AH51: 0 | AI51: =+L51+N51+P51+R51+T51+V51+X51+Z51+AB51+AD51+AF51+AH51 -> 0
B52: 47 | C52: AYSEN | D52: Hospital Regional Coyhaique | E52: MANTENCION PREVENTIVA DRAGER SE DEBE REGULARIZAR ORDEN DE COMPRA AUTORIZADA | F52: 4778-627-TD25 | I52: 5867938 | J52: 22.06.006.003 | L52: 0 | N52: 0 | P52: 0 | R52: 0 | T52: 0 | V52: 0 | X52: 0 | Z52: 0 | AB52: 0 | AD52: 0 | AF52: 0 | AH52: 0 | AI52: =+L52+N52+P52+R52+T52+V52+X52+Z52+AB52+AD52+AF52+AH52 -> 0
B53: 48 | C53: AYSEN | D53: Hospital Regional Coyhaique | E53: MANTENCION PREVENTIVA DRAGER SE DEBE REGULARIZAR ORDEN DE COMPRA AUTORIZADA | F53: 4778-714-TD25 | I53: 9022268 | J53: 22.06.006.003 | L53: 0 | N53: 0 | P53: 0 | R53: 0 | T53: 0 | V53: 0 | X53: 0 | Z53: 0 | AB53: 0 | AD53: 0 | AF53: 0 | AH53: 0 | AI53: =+L53+N53+P53+R53+T53+V53+X53+Z53+AB53+AD53+AF53+AH53 -> 0
B54: 49 | C54: AYSEN | D54: Hospital Regional Coyhaique | E54: MANTENCION PREVENTIVA ALTA TECNOLOGIA MEDICA SE DEBE REGULARIZAR ORDEN DE COMPRA ENVIADA AUTORIZAR | F54: 4778-720-TD25 | I54: 1891426 | J54: 22.06.006.003 | L54: 0 | N54: 0 | P54: 0 | R54: 0 | T54: 0 | V54: 0 | X54: 0 | Z54: 0 | AB54: 0 | AD54: 0 | AF54: 0 | AH54: 0 | AI54: =+L54+N54+P54+R54+T54+V54+X54+Z54+AB54+AD54+AF54+AH54 -> 0
B55: 50 | C55: AYSEN | D55: Hospital Regional Coyhaique | E55: MANTENCION PREVENTIVA DRAGER PROVEEDOR NO FACTURO | F55: 4778-684-TD25 | I55: 419118 | J55: 22.06.006.003 | K55: 4778-684-TD25 | L55: 419118 | N55: 0 | P55: 0 | R55: 0 | T55: 0 | V55: 0 | X55: 0 | Z55: 0 | AB55: 0 | AD55: 0 | AF55: 0 | AH55: 0 | AI55: =+L55+N55+P55+R55+T55+V55+X55+Z55+AB55+AD55+AF55+AH55 -> 419118
B56: 51 | C56: AYSEN | D56: Hospital Regional Coyhaique | E56: MANTENCION PREVENTIVA ARQUIMED SE DEBE REGULARIZAR ORDEN DE COMPRA ENVIADA AUTORIZAR | F56: 4778-723-TD25 | I56: 1723120 | J56: 22.06.006.003 | L56: 0 | N56: 0 | P56: 0 | R56: 0 | T56: 0 | V56: 0 | X56: 0 | Z56: 0 | AB56: 0 | AD56: 0 | AF56: 0 | AH56: 0 | AI56: =+L56+N56+P56+R56+T56+V56+X56+Z56+AB56+AD56+AF56+AH56 -> 0
B57: 52 | C57: AYSEN | D57: Hospital Regional Coyhaique | E57: PRESUPUESTO 2026 PROGRAMADO A SOLICITAR UNIDAD DE EQUIPO MEDICOS | I57: 0 | J57: 22.06.006.003 | L57: 0 | N57: 0 | P57: 0 | R57: 0 | T57: 0 | V57: 0 | X57: 0 | Z57: 0 | AB57: 0 | AD57: 0 | AF57: 0 | AH57: 0 | AI57: =+L57+N57+P57+R57+T57+V57+X58+Z57+AB57+AD57+AF57+AH57 -> 0
B58: 53 | C58: AYSEN | D58: Hospital Regional Coyhaique | E58: Mantencion prenventiva - correctiva-insumo ( Res. Ex. N°10016,04-08-2023) ( Res. Ex.14499, 3-10-2024) Andover Critico | F58: en curso 2026 | G58: 46238 | H58: 46387 | I58: =4329719*5 -> 21648595 | J58: 22.06.006.003 | L58: 0 | N58: 0 | P58: 0 | R58: 0 | T58: 0 | V58: 0 | X58: 0 | Z58: 0 | AB58: 0 | AD58: 0 | AF58: 0 | AH58: 0 | AI58: =+L58+N58+P58+R58+T58+V58+X59+Z58+AB58+AD58+AF58+AH58 -> 0
B59: 54 | C59: AYSEN | D59: Hospital Regional Coyhaique | E59: MANTENCION PREVENTIVA EQUIPOS DE IMAGENOLOGIA URG 15 PHILIPS RELEVANTE | F59: en curso 2026 | G59: 45843 | H59: 46387 | I59: 87844848 | J59: 22.06.006.003 | L59: 0 | N59: 0 | P59: 0 | R59: 0 | T59: 0 | V59: 0 | X59: 0 | Z59: 0 | AB59: 0 | AD59: 0 | AF59: 0 | AH59: 0 | AI59: =+L59+N59+P59+R59+T59+V59+X60+Z59+AB59+AD59+AF59+AH59 -> 0
B60: 55 | C60: AYSEN | D60: Hospital Regional Coyhaique | E60: MANTENCION DE RESONADOR relevante | F60: en curso 2026 | G60: 01-10-206 | H60: 46387 | I60: 20518574 | J60: 22.06.006.003 | L60: 0 | N60: 0 | P60: 0 | R60: 0 | T60: 0 | V60: 0 | X60: 0 | Z60: 0 | AB60: 0 | AD60: 0 | AF60: 0 | AH60: 0 | AI60: =+L60+N60+P60+R60+T60+V60+X61+Z60+AB60+AD60+AF60+AH60 -> 0
B61: 56 | C61: AYSEN | D61: Hospital Regional Coyhaique | E61: Mantencion preventiva portatil de agfa RELEVANTE | F61: en curso 2026 | G61: 46143 | H61: 46387 | I61: =881647*8 -> 7053176 | J61: 22.06.006.003 | L61: 0 | N61: 0 | P61: 0 | R61: 0 | T61: 0 | V61: 0 | X61: 0 | Z61: 0 | AB61: 0 | AD61: 0 | AF61: 0 | AH61: 0 | AI61: =+L61+N61+P61+R61+T61+V61+X63+Z61+AB61+AD61+AF61+AH61 -> 0
C62: AYSEN | D62: Hospital Regional Coyhaique | E62: Mantencion prenventiva - correctiva-insumo ( Res. Ex. N°10016,04-08-2023) ( Res. Ex.14499, 3-10-2024) Andover | F62: Res Ex. 14499 | G62: 45568 | H62: 46203 | I62: =1393300*6 -> 8359800 | J62: 22.06.006.003 | K62: 1366597-311-TD26 | L62: 0 | N62: 0 | P62: 0 | R62: 0 | T62: 0 | V62: 0 | X62: 0 | Z62: 0 | AB62: 0 | AD62: 0 | AF62: 0 | AH62: 0 | AI62: =+L62+N62+P62+R62+T62+V62+X64+Z62+AB62+AD62+AF62+AH62 -> 0
B63: 57 | C63: AYSEN | D63: Hospital Regional Coyhaique | E63: Mantencion prenventiva - correctiva-insumo ( Res. Ex. N°10016,04-08-2023) ( Res. Ex.14499, 3-10-2024) Andover | F63: Res Ex. 10016 | G63: 45142 | H63: 46238 | I63: =2936419*7 -> 20554933 | J63: 22.06.006.003 | K63: 1366597-308-TD26 | L63: 0 | N63: 0 | P63: 0 | R63: 0 | T63: 0 | V63: 0 | X63: 0 | Z63: 0 | AB63: 0 | AD63: 0 | AF63: 0 | AH63: 0 | AI63: =+L63+N63+P63+R63+T63+V63+X64+Z63+AB63+AD63+AF63+AH63 -> 0
B64: 58 | C64: AYSEN | D64: Hospital Regional Coyhaique | E64: MANTENCION PREVENTIVA EQUIPOS DE IMAGENOLOGIA URG 15 PHILIPS RELEVANTE | F64: 10115 | G64: 45478 | H64: 45843 | I64: 84466200 | J64: 22.06.006.003 | K64: 1366597-329-TD26 | L64: 0 | N64: 0 | P64: 0 | R64: 0 | T64: 0 | V64: 0 | X64: 0 | Z64: 0 | AB64: 0 | AD64: 0 | AF64: 0 | AH64: 0 | AI64: =+L64+N64+P64+R64+T64+V64+X65+Z64+AB64+AD64+AF64+AH64 -> 0
B65: 59 | C65: AYSEN | D65: Hospital Regional Coyhaique | E65: MANTENCION DE RESONADOR relevante | F65: 16341 | G65: 45931 | H65: 46296 | I65: 102529870 | J65: 22.06.006.003 | K65: 1366597-328-TD26 | L65: 0 | N65: 0 | P65: 0 | R65: 0 | T65: 0 | V65: 0 | X65: 0 | Z65: 0 | AB65: 0 | AD65: 0 | AF65: 0 | AH65: 0 | AI65: =+L65+N65+P65+R65+T65+V65+X66+Z65+AB65+AD65+AF65+AH65 -> 0
B66: 60 | C66: AYSEN | D66: Hospital Regional Coyhaique | E66: MANTENCION PROPUESTA CONVENIO BRONCE PLATIUN SOL 9 AGFA relevante | F66: 6346 | G66: 45413 | H66: 46142 | I66: =877587*4 -> 3510348 | J66: 22.06.006.003 | L66: 0 | N66: 0 | P66: 0 | R66: 0 | T66: 0 | V66: 0 | X66: 0 | Z66: 0 | AB66: 0 | AD66: 0 | AF66: 0 | AH66: 0 | AI66: =+L66+N66+P66+R66+T66+V66+X67+Z66+AB66+AD66+AF66+AH66 -> 0
B67: 61 | C67: AYSEN | D67: Hospital Regional Coyhaique | E67: EXT N 7 | F67: 4778-24-TD26 | I67: 9698262 | J67: 22.06.006.003 | K67: 4778-24-TD26 | L67: 0 | N67: 0 | P67: 0 | R67: 0 | T67: 0 | V67: 0 | X67: 0 | Z67: 0 | AB67: 0 | AD67: 0 | AF67: 0 | AH67: 0 | AI67: =+L67+N67+P67+R67+T67+V67+X68+Z67+AB67+AD67+AF67+AH67 -> 0
B68: 62 | C68: AYSEN | D68: Hospital Regional Coyhaique | E68: EXT N 10 | I68: 9377200 | J68: 22.06.006.003 | L68: 0 | N68: 0 | P68: 0 | R68: 0 | T68: 0 | V68: 0 | X68: 0 | Z68: 0 | AB68: 0 | AD68: 0 | AF68: 0 | AH68: 0 | AI68: =+L68+N68+P68+R68+T68+V68+X69+Z68+AB68+AD68+AF68+AH68 -> 0
B69: 63 | C69: AYSEN | D69: Hospital Regional Coyhaique | E69: EXT N 14 | F69: 4778-40-TD26 | I69: 1725702 | J69: 22.06.006.003 | L69: 0 | N69: 0 | P69: 0 | R69: 0 | T69: 0 | V69: 0 | X69: 0 | Z69: 0 | AB69: 0 | AD69: 0 | AF69: 0 | AH69: 0 | AI69: =+L69+N69+P69+R69+T69+V69+X70+Z69+AB69+AD69+AF69+AH69 -> 0
B70: 64 | C70: AYSEN | D70: Hospital Regional Coyhaique | E70: EXT N 15 | F70: 4778-42-TD26 | I70: 5295500 | J70: 22.06.006.003 | L70: 0 | N70: 0 | P70: 0 | R70: 0 | T70: 0 | V70: 0 | X70: 0 | Z70: 0 | AB70: 0 | AD70: 0 | AF70: 0 | AH70: 0 | AI70: =+L70+N70+P70+R70+T70+V70+X71+Z70+AB70+AD70+AF70+AH70 -> 0
B71: 65 | C71: AYSEN | D71: Hospital Regional Coyhaique | E71: EXT N 16 | I71: 22164278 | J71: 22.06.006.003 | L71: 0 | N71: 0 | P71: 0 | R71: 0 | T71: 0 | V71: 0 | X71: 0 | Z71: 0 | AB71: 0 | AD71: 0 | AF71: 0 | AH71: 0 | AI71: =+L71+N71+P71+R71+T71+V71+X72+Z71+AB71+AD71+AF71+AH71 -> 0
B72: 66 | C72: AYSEN | D72: Hospital Regional Coyhaique | E72: EXT N 18 | I72: 1156680 | J72: 22.06.006.003 | L72: 0 | N72: 0 | P72: 0 | R72: 0 | T72: 0 | V72: 0 | X72: 0 | Z72: 0 | AB72: 0 | AD72: 0 | AF72: 0 | AH72: 0 | AI72: =+L72+N72+P72+R72+T72+V72+X73+Z72+AB72+AD72+AF72+AH72 -> 0
B73: 67 | C73: AYSEN | D73: Hospital Regional Coyhaique | E73: EXT N 21 | I73: 5938100 | J73: 22.06.006.003 | L73: 0 | N73: 0 | P73: 0 | R73: 0 | T73: 0 | V73: 0 | X73: 0 | Z73: 0 | AB73: 0 | AD73: 0 | AF73: 0 | AH73: 0 | AI73: =+L73+N73+P73+R73+T73+V73+X74+Z73+AB73+AD73+AF73+AH73 -> 0
B74: 68 | C74: AYSEN | D74: Hospital Regional Coyhaique | E74: EXT N 23 | F74: 4778-39-TD26 | I74: 1023400 | J74: 22.06.006.003 | K74: 4778-39-TD26 | L74: 0 | N74: 0 | P74: 0 | R74: 0 | T74: 0 | V74: 0 | X74: 0 | Z74: 0 | AB74: 0 | AD74: 0 | AF74: 0 | AH74: 0 | AI74: =+L74+N74+P74+R74+T74+V74+X75+Z74+AB74+AD74+AF74+AH74 -> 0
B75: 69 | C75: AYSEN | D75: Hospital Regional Coyhaique | E75: EXT N 25 | I75: 1297100 | J75: 22.06.006.003 | L75: 0 | N75: 0 | P75: 0 | R75: 0 | T75: 0 | V75: 0 | X75: 0 | Z75: 0 | AB75: 0 | AD75: 0 | AF75: 0 | AH75: 0 | AI75: =+L75+N75+P75+R75+T75+V75+X76+Z75+AB75+AD75+AF75+AH75 -> 0
B76: 70 | C76: AYSEN | D76: Hospital Regional Coyhaique | E76: EXT N 26 | F76: 4778-41-TD26 | I76: 6091420 | J76: 22.06.006.003 | L76: 0 | N76: 0 | P76: 0 | R76: 0 | T76: 0 | V76: 0 | X76: 0 | Z76: 0 | AB76: 0 | AD76: 0 | AF76: 0 | AH76: 0 | AI76: =+L76+N76+P76+R76+T76+V76+X77+Z76+AB76+AD76+AF76+AH76 -> 0
B77: 71 | C77: AYSEN | D77: Hospital Regional Coyhaique | E77: EXT N 28 | I77: 2832200 | J77: 22.06.006.003 | L77: 0 | N77: 0 | P77: 0 | R77: 0 | T77: 0 | V77: 0 | X77: 0 | Z77: 0 | AB77: 0 | AD77: 0 | AF77: 0 | AH77: 0 | AI77: =+L77+N77+P77+R77+T77+V77+X78+Z77+AB77+AD77+AF77+AH77 -> 0
B78: 72 | C78: AYSEN | D78: Hospital Regional Coyhaique | E78: EXT N 29 | I78: 14586568 | J78: 22.06.006.003 | L78: 0 | N78: 0 | P78: 0 | R78: 0 | T78: 0 | V78: 0 | X78: 0 | Z78: 0 | AB78: 0 | AD78: 0 | AF78: 0 | AH78: 0 | AI78: =+L78+N78+P78+R78+T78+V78+X79+Z78+AB78+AD78+AF78+AH78 -> 0
B79: 73 | C79: AYSEN | D79: Hospital Regional Coyhaique | E79: EXT N 32 | I79: 11810750 | J79: 22.06.006.003 | L79: 0 | N79: 0 | P79: 0 | R79: 0 | T79: 0 | V79: 0 | X79: 0 | Z79: 0 | AB79: 0 | AD79: 0 | AF79: 0 | AH79: 0 | AI79: =+L79+N79+P79+R79+T79+V79+X80+Z79+AB79+AD79+AF79+AH79 -> 0
B80: 74 | C80: AYSEN | D80: Hospital Regional Coyhaique | E80: EXT N 34 | I80: 1739711 | J80: 22.06.006.003 | L80: 0 | N80: 0 | P80: 0 | R80: 0 | T80: 0 | V80: 0 | X80: 0 | Z80: 0 | AB80: 0 | AD80: 0 | AF80: 0 | AH80: 0 | AI80: =+L80+N80+P80+R80+T80+V80+X81+Z80+AB80+AD80+AF80+AH80 -> 0
B81: 75 | C81: AYSEN | D81: Hospital Regional Coyhaique | E81: 4778-506-TD25 | F81: 4778-506-TD25 | I81: 4231640 | J81: 22.06.006.003 | L81: 0 | N81: 0 | P81: 0 | R81: 0 | T81: 0 | V81: 0 | X81: 0 | Z81: 0 | AB81: 0 | AD81: 0 | AF81: 0 | AH81: 0 | AI81: =+L81+N81+P81+R81+T81+V81+X82+Z81+AB81+AD81+AF81+AH81 -> 0
B82: 76 | C82: AYSEN | D82: Hospital Regional Coyhaique | J82: 22.06.006.003 | L82: 0 | N82: 0 | P82: 0 | R82: 0 | T82: 0 | V82: 0 | X82: 0 | Z82: 0 | AB82: 0 | AD82: 0 | AF82: 0 | AH82: 0 | AI82: =+L82+N82+P82+R82+T82+V82+X83+Z82+AB82+AD82+AF82+AH82 -> 0
B83: 77 | C83: AYSEN | D83: Hospital Regional Coyhaique | J83: 22.06.006.003 | L83: 0 | N83: 0 | P83: 0 | R83: 0 | T83: 0 | V83: 0 | X83: 0 | Z83: 0 | AB83: 0 | AD83: 0 | AF83: 0 | AH83: 0 | AI83: =+L83+N83+P83+R83+T83+V83+X84+Z83+AB83+AD83+AF83+AH83 -> 0
B84: 78 | C84: AYSEN | D84: Hospital Regional Coyhaique | J84: 22.06.006.003 | L84: 0 | N84: 0 | P84: 0 | R84: 0 | T84: 0 | V84: 0 | X84: 0 | Z84: 0 | AB84: 0 | AD84: 0 | AF84: 0 | AH84: 0 | AI84: =+L84+N84+P84+R84+T84+V84+X85+Z84+AB84+AD84+AF84+AH84 -> 0
B85: 79 | C85: AYSEN | D85: Hospital Regional Coyhaique | J85: 22.06.006.003 | L85: 0 | N85: 0 | P85: 0 | R85: 0 | T85: 0 | V85: 0 | X85: 0 | Z85: 0 | AB85: 0 | AD85: 0 | AF85: 0 | AH85: 0 | AI85: =+L85+N85+P85+R85+T85+V85+X86+Z85+AB85+AD85+AF85+AH85 -> 0
B86: 80 | C86: AYSEN | D86: Hospital Regional Coyhaique | J86: 22.06.006.003 | L86: 0 | N86: 0 | P86: 0 | R86: 0 | T86: 0 | V86: 0 | X86: 0 | Z86: 0 | AB86: 0 | AD86: 0 | AF86: 0 | AH86: 0 | AI86: =+L86+N86+P86+R86+T86+V86+X87+Z86+AB86+AD86+AF86+AH86 -> 0
B87: 81 | C87: AYSEN | D87: Hospital Regional Coyhaique | J87: 22.06.006.003 | L87: 0 | N87: 0 | P87: 0 | R87: 0 | T87: 0 | V87: 0 | X87: 0 | Z87: 0 | AB87: 0 | AD87: 0 | AF87: 0 | AH87: 0 | AI87: =+L87+N87+P87+R87+T87+V87+X88+Z87+AB87+AD87+AF87+AH87 -> 0
B88: 82 | C88: AYSEN | D88: Hospital Regional Coyhaique | J88: 22.06.006.003 | L88: 0 | N88: 0 | P88: 0 | R88: 0 | T88: 0 | V88: 0 | X88: 0 | Z88: 0 | AB88: 0 | AD88: 0 | AF88: 0 | AH88: 0 | AI88: =+L88+N88+P88+R88+T88+V88+X89+Z88+AB88+AD88+AF88+AH88 -> 0
B89: 83 | C89: AYSEN | D89: Hospital Regional Coyhaique | J89: 22.06.006.003 | L89: 0 | N89: 0 | P89: 0 | R89: 0 | T89: 0 | V89: 0 | X89: 0 | Z89: 0 | AB89: 0 | AD89: 0 | AF89: 0 | AH89: 0 | AI89: =+L89+N89+P89+R89+T89+V89+X90+Z89+AB89+AD89+AF89+AH89 -> 0
B90: 84 | C90: AYSEN | D90: Hospital Regional Coyhaique | J90: 22.06.006.003 | L90: 0 | N90: 0 | P90: 0 | R90: 0 | T90: 0 | V90: 0 | X90: 0 | Z90: 0 | AB90: 0 | AD90: 0 | AF90: 0 | AH90: 0 | AI90: =+L90+N90+P90+R90+T90+V90+X91+Z90+AB90+AD90+AF90+AH90 -> 0
B91: 85 | C91: AYSEN | D91: Hospital Regional Coyhaique | J91: 22.06.006.003 | L91: 0 | N91: 0 | P91: 0 | R91: 0 | T91: 0 | V91: 0 | X91: 0 | Z91: 0 | AB91: 0 | AD91: 0 | AF91: 0 | AH91: 0 | AI91: =+L91+N91+P91+R91+T91+V91+X92+Z91+AB91+AD91+AF91+AH91 -> 0
B92: 86 | C92: AYSEN | D92: Hospital Regional Coyhaique | J92: 22.06.006.003 | L92: 0 | N92: 0 | P92: 0 | R92: 0 | T92: 0 | V92: 0 | X92: 0 | Z92: 0 | AB92: 0 | AD92: 0 | AF92: 0 | AH92: 0 | AI92: =+L92+N92+P92+R92+T92+V92+X93+Z92+AB92+AD92+AF92+AH92 -> 0
B93: 87 | C93: AYSEN | D93: Hospital Regional Coyhaique | J93: 22.06.006.003 | L93: 0 | N93: 0 | P93: 0 | R93: 0 | T93: 0 | V93: 0 | X93: 0 | Z93: 0 | AB93: 0 | AD93: 0 | AF93: 0 | AH93: 0 | AI93: =+L93+N93+P93+R93+T93+V93+X94+Z93+AB93+AD93+AF93+AH93 -> 0
... B140: 134 | C140: AYSEN | D140: Hospital Regional Coyhaique | J140: 22.06.006.003 | L140: 0 | N140: 0 | P140: 0 | R140: 0 | T140: 0 | V140: 0 | X140: 0 | Z140: 0 | AB140: 0 | AD140: 0 | AF140: 0 | AH140: 0 | AI140: =+L140+N140+P140+R140+T140+V140+X141+Z140+AB140+AD140+AF140+AH140 -> 0
B141: 135 | C141: AYSEN | D141: Hospital Regional Coyhaique | J141: 22.06.006.003 | L141: 0 | N141: 0 | P141: 0 | R141: 0 | T141: 0 | V141: 0 | X141: 0 | Z141: 0 | AB141: 0 | AD141: 0 | AF141: 0 | AH141: 0 | AI141: =+L141+N141+P141+R141+T141+V141+X141+Z141+AB141+AD141+AF141+AH141 -> 0
AI142: =SUM(AI8:AI141) -> 97382016
B144: SEGUIMIENTO GASTO MANTENIMIENTO CORRECTIVO / ADQUISICIÓN DE REPUESTOS / ADQUISICIÓN DE INSUMOS / ADQUISICIÓN DE ACCESORIOS
I146: CONTROL MENSUAL EJECUCIÓN
I147: ENERO | K147: FEBRERO | M147: MARZO | O147: ABRIL | Q147: MAYO | S147: JUNIO | U147: JULIO | W147: AGOSTO | Y147: SEPTIEMBRE | AA147: OCTUBRE | AC147: NOVIEMBRE | AE147: DICIEMBRE
B148: Nº | C148: SERVICIO DE SALUD | D148: ESTABLECIMIENTO | E148: DESCRIPCIÓN DE LA COMPRA | F148: TIPO DE GASTO CORRECTIVO | G148: MONTO | H148: SUBASIGNACIÓN SIGFE | I148: N° ORDEN DE COMPRA | J148: MONTO ($) | K148: N° ORDEN DE COMPRA | L148: MONTO ($) | M148: N° ORDEN DE COMPRA | N148: MONTO ($) | O148: N° ORDEN DE COMPRA | P148: MONTO ($) | Q148: N° ORDEN DE COMPRA | R148: MONTO ($) | S148: N° ORDEN DE COMPRA | T148: MONTO ($) | U148: N° ORDEN DE COMPRA | V148: MONTO ($) | W148: N° ORDEN DE COMPRA | X148: MONTO ($) | Y148: N° ORDEN DE COMPRA | Z148: MONTO ($) | AA148: N° ORDEN DE COMPRA | AB148: MONTO ($) | AC148: N° ORDEN DE COMPRA | AD148: MONTO ($) | AE148: N° ORDEN DE COMPRA | AF148: MONTO ($) | AG148: TOTAL
B149: 1 | C149: AYSEN | D149: Hospital Regional Coyhaique | E149: EXT N 1 | F149: MANTENIMIENTO CORRECTIVO | G149: 714000 | H149: 22.06.006.004 | I149: 4778-22-TD26 | J149: 0 | L149: 0 | N149: 0 | P149: 0 | R149: 0 | T149: 0 | V149: 0 | X149: 0 | Z149: 0 | AB149: 0 | AD149: 0 | AF149: 0 | AG149: =+J149+L149+N149+P149+R149+T150+V149+X149+Z149+AB149+AD149+AF149 -> 0
B150: 2 | C150: AYSEN | D150: Hospital Regional Coyhaique | E150: EXT N 2 | F150: MANTENIMIENTO CORRECTIVO | G150: 1176910 | H150: 22.06.006.004 | I150: 4778-21-TD26 | J150: 0 | L150: 0 | N150: 0 | P150: 0 | R150: 0 | T150: 0 | V150: 0 | X150: 0 | Z150: 0 | AB150: 0 | AD150: 0 | AF150: 0 | AG150: =+J150+L150+N150+P150+R150+T151+V150+X150+Z150+AB150+AD150+AF150 -> 0
B151: 3 | C151: AYSEN | D151: Hospital Regional Coyhaique | E151: EXT N 3 | F151: MANTENIMIENTO CORRECTIVO | G151: 1600550 | H151: 22.06.006.004 | I151: 4778-23-TD26 | J151: 0 | L151: 0 | N151: 0 | P151: 0 | R151: 0 | T151: 0 | V151: 0 | X151: 0 | Z151: 0 | AB151: 0 | AD151: 0 | AF151: 0 | AG151: =+J151+L151+N151+P151+R151+T152+V151+X151+Z151+AB151+AD151+AF151 -> 0
B152: 4 | C152: AYSEN | D152: Hospital Regional Coyhaique | E152: EXT N 4 | F152: MANTENIMIENTO CORRECTIVO | G152: 828240 | H152: 22.06.006.004 | I152: 4778-20-TD26 | J152: 0 | L152: 0 | N152: 0 | P152: 0 | R152: 0 | T152: 0 | V152: 0 | X152: 0 | Z152: 0 | AB152: 0 | AD152: 0 | AF152: 0 | AG152: =+J152+L152+N152+P152+R152+T153+V152+X152+Z152+AB152+AD152+AF152 -> 0
B153: 5 | C153: AYSEN | D153: Hospital Regional Coyhaique | E153: EXT N 5 | F153: MANTENIMIENTO CORRECTIVO | G153: 48355650 | H153: 22.06.006.004 | I153: 4778-16-TD26 | J153: 0 | L153: 0 | N153: 0 | P153: 0 | R153: 0 | T153: 0 | V153: 0 | X153: 0 | Z153: 0 | AB153: 0 | AD153: 0 | AF153: 0 | AG153: =+J153+L153+N153+P153+R153+T153+V153+X153+Z153+AB153+AD153+AF153 -> 0
B154: 6 | C154: AYSEN | D154: Hospital Regional Coyhaique | E154: EXT N 6 | F154: ADQUISICION DE ACCESORIOS | G154: 1606500 | H154: 22.06.006.004 | I154: 4778-25-TD26 | J154: 0 | L154: 0 | N154: 0 | P154: 0 | R154: 0 | T154: 0 | V154: 0 | X154: 0 | Z154: 0 | AB154: 0 | AD154: 0 | AF154: 0 | AG154: =+J154+L154+N154+P154+R154+T154+V154+X154+Z154+AB154+AD154+AF154 -> 0
B155: 7 | C155: AYSEN | D155: Hospital Regional Coyhaique | E155: EXT N 8 | F155: ADQUISICIÓN DE REPUESTOS | G155: 3808000 | H155: 22.06.006.004 | I155: 4778-26-TD26 | J155: 0 | L155: 0 | N155: 0 | P155: 0 | R155: 0 | T155: 0 | V155: 0 | X155: 0 | Z155: 0 | AB155: 0 | AD155: 0 | AF155: 0 | AG155: =+J155+L155+N155+P155+R155+T155+V155+X155+Z155+AB155+AD155+AF155 -> 0
B156: 8 | C156: AYSEN | D156: Hospital Regional Coyhaique | E156: EXT N 9 | F156: MANTENIMIENTO CORRECTIVO | G156: 6257809 | H156: 22.06.006.004 | J156: 0 | L156: 0 | N156: 0 | P156: 0 | R156: 0 | T156: 0 | V156: 0 | X156: 0 | Z156: 0 | AB156: 0 | AD156: 0 | AF156: 0 | AG156: =+J156+L156+N156+P156+R156+T156+V156+X156+Z156+AB156+AD156+AF156 -> 0
B157: 9 | C157: AYSEN | D157: Hospital Regional Coyhaique | E157: EXT N 11 | F157: ADQUISICIÓN DE REPUESTOS | G157: 589050 | H157: 22.06.006.004 | J157: 0 | L157: 0 | N157: 0 | P157: 0 | R157: 0 | T157: 0 | V157: 0 | X157: 0 | Z157: 0 | AB157: 0 | AD157: 0 | AF157: 0 | AG157: =+J157+L157+N157+P157+R157+T157+V157+X157+Z157+AB157+AD157+AF157 -> 0
...

Sheet TABLA CÁLCULO
A3: Etiquetas de fila | B3: Suma de FRECUENCIA ANUAL DE MANTENIMIENTO
A4: CRÍTICO | B4: 6
A5: IM ≥ 12 | B5: 6
A6: RELEVANTE | B6: 3
A7: (en blanco)
A8: Total general | B8: 15
A12: N° MP PROGRAMADAS | O12: TOTAL MP PROGRAMADAS | P12: =+GETPIVOTDATA("FRECUENCIA ANUAL DE MANTENIMIENTO",$A$49,"AÑO INGRESO A PLAN DE MANTENIMIENTO (2023 / 2024 / 2025 / 2026)",2023) -> 10
A13: N° MP EJECUTADAS | B13: =+COUNTIF('CATASTRO Y PLANIFICACIÓN MP'!Y16:Y4956,"√") -> 76 | C13: =+COUNTIF('CATASTRO Y PLANIFICACIÓN MP'!Z16:Z4956,"√") -> 0 | D13: =+COUNTIF('CATASTRO Y PLANIFICACIÓN MP'!AA16:AA4956,"√") -> 0 | E13: =+COUNTIF('CATASTRO Y PLANIFICACIÓN MP'!AB16:AB4956,"√") -> 0 | F13: =+COUNTIF('CATASTRO Y PLANIFICACIÓN MP'!AC16:AC4956,"√") -> 0 | G13: =+COUNTIF('CATASTRO Y PLANIFICACIÓN MP'!AD16:AD4956,"√") -> 0 | H13: =+COUNTIF('CATASTRO Y PLANIFICACIÓN MP'!AE16:AE4956,"√") -> 0 | I13: =+COUNTIF('CATASTRO Y PLANIFICACIÓN MP'!AF16:AF4956,"√") -> 0 | ... M13: =+COUNTIF('CATASTRO Y PLANIFICACIÓN MP'!AJ16:AJ4956,"√") -> 0 | O13: TOTAL MP EJECUTADAS | P13: =+SUM(B13:M13) -> 76 | R13: X | S13: PROGRAMADO | U13: CRÍTICO | W13: SI | Y13: 2023 | AA13: INTERNO | AC13: 1 | AE13: PROPIO | AF13: BUENO
A14: N° MP REPROGRAMADAS | B14: =+COUNTIF('CATASTRO Y PLANIFICACIÓN MP'!Y16:Y4957,"ꓣ") -> 0 | C14: =+COUNTIF('CATASTRO Y PLANIFICACIÓN MP'!Z16:Z4957,"ꓣ") -> 0 | D14: =+COUNTIF('CATASTRO Y PLANIFICACIÓN MP'!AA16:AA4957,"ꓣ") -> 0 | E14: =+COUNTIF('CATASTRO Y PLANIFICACIÓN MP'!AB16:AB4957,"ꓣ") -> 0 | F14: =+COUNTIF('CATASTRO Y PLANIFICACIÓN MP'!AC16:AC4957,"ꓣ") -> 0 | G14: =+COUNTIF('CATASTRO Y PLANIFICACIÓN MP'!AD16:AD4957,"ꓣ") -> 0 | H14: =+COUNTIF('CATASTRO Y PLANIFICACIÓN MP'!AE16:AE4957,"ꓣ") -> 0 | I14: =+COUNTIF('CATASTRO Y PLANIFICACIÓN MP'!AF16:AF4957,"ꓣ") -> 0 | ... M14: =+COUNTIF('CATASTRO Y PLANIFICACIÓN MP'!AJ16:AJ4957,"ꓣ") -> 0 | O14: TOTAL MP REPROGRAMADAS | P14: =+SUM(B14:M14) -> 0 | R14: √ | S14: REALIZADO | U14: RELEVANTE | W14: NO | Y14: 2024 | AA14: EXTERNO | AC14: 2 | AE14: ARRIENDO | AF14: REGULAR
O15: TOTAL MP PROGRAMADAS EQC | P15: =+GETPIVOTDATA("FRECUENCIA ANUAL DE MANTENIMIENTO",$A$49,"CRÍTICO/ RELEVANTE / IM≥12 / NO APLICA","CRÍTICO","AÑO INGRESO A PLAN DE MANTENIMIENTO (2023 / 2024 / 2025 / 2026)",2023) -> 6 | R15: ꓣ | S15: REPROGRAMADO | U15: IM ≥ 12 | Y15: 2025 | AC15: 3 | AE15: COMODATO | AF15: MALO
A16: N° MP EJECUTADAS EQC | B16: =+COUNTIFS('CATASTRO Y PLANIFICACIÓN MP'!$O$16:$O$4951,"CRÍTICO",'CATASTRO Y PLANIFICACIÓN MP'!Y16:Y4951,"√") -> 65 | C16: =+COUNTIFS('CATASTRO Y PLANIFICACIÓN MP'!$O$16:$O$4951,"CRÍTICO",'CATASTRO Y PLANIFICACIÓN MP'!Z16:Z4951,"√") -> 0 | D16: =+COUNTIFS('CATASTRO Y PLANIFICACIÓN MP'!$O$16:$O$4951,"CRÍTICO",'CATASTRO Y PLANIFICACIÓN MP'!AA16:AA4951,"√") -> 0 | E16: =+COUNTIFS('CATASTRO Y PLANIFICACIÓN MP'!$O$16:$O$4951,"CRÍTICO",'CATASTRO Y PLANIFICACIÓN MP'!AB16:AB4951,"√") -> 0 | F16: =+COUNTIFS('CATASTRO Y PLANIFICACIÓN MP'!$O$16:$O$4951,"CRÍTICO",'CATASTRO Y PLANIFICACIÓN MP'!AC16:AC4951,"√") -> 0 | G16: =+COUNTIFS('CATASTRO Y PLANIFICACIÓN MP'!$O$16:$O$4951,"CRÍTICO",'CATASTRO Y PLANIFICACIÓN MP'!AD16:AD4951,"√") -> 0 | H16: =+COUNTIFS('CATASTRO Y PLANIFICACIÓN MP'!$O$16:$O$4951,"CRÍTICO",'CATASTRO Y PLANIFICACIÓN MP'!AE16:AE4951,"√") -> 0 | I16: =+COUNTIFS('CATASTRO Y PLANIFICACIÓN MP'!$O$16:$O$4951,"CRÍTICO",'CATASTRO Y PLANIFICACIÓN MP'!AF16:AF4951,"√") -> 0 | ... M16: =+COUNTIFS('CATASTRO Y PLANIFICACIÓN MP'!$O$16:$O$4951,"CRÍTICO",'CATASTRO Y PLANIFICACIÓN MP'!AJ16:AJ4951,"√") -> 0 | O16: TOTAL MP PROGRAMADAS EQR | P16: =+GETPIVOTDATA("FRECUENCIA ANUAL DE MANTENIMIENTO",$A$49,"CRÍTICO/ RELEVANTE / IM≥12 / NO APLICA","RELEVANTE","AÑO INGRESO A PLAN DE MANTENIMIENTO (2023 / 2024 / 2025 / 2026)",2023) -> 1 | U16: NO APLICA | Y16: 2026 | AC16: 4 | AE16: PRÉSTAMO
A17: N° MP EJECUTADAS EQR | B17: =+COUNTIFS('CATASTRO Y PLANIFICACIÓN MP'!$O$16:$O$4951,"RELEVANTE",'CATASTRO Y PLANIFICACIÓN MP'!Y16:Y4951,"√") -> 11 | C17: =+COUNTIFS('CATASTRO Y PLANIFICACIÓN MP'!$O$16:$O$4951,"RELEVANTE",'CATASTRO Y PLANIFICACIÓN MP'!Z16:Z4951,"√") -> 0 | D17: =+COUNTIFS('CATASTRO Y PLANIFICACIÓN MP'!$O$16:$O$4951,"RELEVANTE",'CATASTRO Y PLANIFICACIÓN MP'!AA16:AA4951,"√") -> 0 | E17: =+COUNTIFS('CATASTRO Y PLANIFICACIÓN MP'!$O$16:$O$4951,"RELEVANTE",'CATASTRO Y PLANIFICACIÓN MP'!AB16:AB4951,"√") -> 0 | F17: =+COUNTIFS('CATASTRO Y PLANIFICACIÓN MP'!$O$16:$O$4951,"RELEVANTE",'CATASTRO Y PLANIFICACIÓN MP'!AC16:AC4951,"√") -> 0 | G17: =+COUNTIFS('CATASTRO Y PLANIFICACIÓN MP'!$O$16:$O$4951,"RELEVANTE",'CATASTRO Y PLANIFICACIÓN MP'!AD16:AD4951,"√") -> 0 | H17: =+COUNTIFS('CATASTRO Y PLANIFICACIÓN MP'!$O$16:$O$4951,"RELEVANTE",'CATASTRO Y PLANIFICACIÓN MP'!AE16:AE4951,"√") -> 0 | I17: =+COUNTIFS('CATASTRO Y PLANIFICACIÓN MP'!$O$16:$O$4951,"RELEVANTE",'CATASTRO Y PLANIFICACIÓN MP'!AF16:AF4951,"√") -> 0 | ... M17: =+COUNTIFS('CATASTRO Y PLANIFICACIÓN MP'!$O$16:$O$4951,"RELEVANTE",'CATASTRO Y PLANIFICACIÓN MP'!AJ16:AJ4951,"√") -> 0 | O17: TOTAL MP PROGRAMADAS IM≥12 | P17: =+GETPIVOTDATA("FRECUENCIA ANUAL DE MANTENIMIENTO",$A$49,"CRÍTICO/ RELEVANTE / IM≥12 / NO APLICA","IM ≥ 12","AÑO INGRESO A PLAN DE MANTENIMIENTO (2023 / 2024 / 2025 / 2026)",2023) -> 3 | AC17: 6
A18: N° MP EJECUTADAS IM≥12 | B18: =+COUNTIFS('CATASTRO Y PLANIFICACIÓN MP'!$O$16:$O$4951,"IM ≥ 12",'CATASTRO Y PLANIFICACIÓN MP'!Y16:Y4951,"√") -> 0 | C18: =+COUNTIFS('CATASTRO Y PLANIFICACIÓN MP'!$O$16:$O$4951,"IM ≥ 12",'CATASTRO Y PLANIFICACIÓN MP'!Z16:Z4951,"√") -> 0 | D18: =+COUNTIFS('CATASTRO Y PLANIFICACIÓN MP'!$O$16:$O$4951,"IM ≥ 12",'CATASTRO Y PLANIFICACIÓN MP'!AA16:AA4951,"√") -> 0 | E18: =+COUNTIFS('CATASTRO Y PLANIFICACIÓN MP'!$O$16:$O$4951,"IM ≥ 12",'CATASTRO Y PLANIFICACIÓN MP'!AB16:AB4951,"√") -> 0 | F18: =+COUNTIFS('CATASTRO Y PLANIFICACIÓN MP'!$O$16:$O$4951,"IM ≥ 12",'CATASTRO Y PLANIFICACIÓN MP'!AC16:AC4951,"√") -> 0 | G18: =+COUNTIFS('CATASTRO Y PLANIFICACIÓN MP'!$O$16:$O$4951,"IM ≥ 12",'CATASTRO Y PLANIFICACIÓN MP'!AD16:AD4951,"√") -> 0 | H18: =+COUNTIFS('CATASTRO Y PLANIFICACIÓN MP'!$O$16:$O$4951,"IM ≥ 12",'CATASTRO Y PLANIFICACIÓN MP'!AE16:AE4951,"√") -> 0 | I18: =+COUNTIFS('CATASTRO Y PLANIFICACIÓN MP'!$O$16:$O$4951,"IM ≥ 12",'CATASTRO Y PLANIFICACIÓN MP'!AF16:AF4951,"√") -> 0 | ... M18: =+COUNTIFS('CATASTRO Y PLANIFICACIÓN MP'!$O$16:$O$4951,"IM ≥ 12",'CATASTRO Y PLANIFICACIÓN MP'!AJ16:AJ4951,"√") -> 0 | O18: TOTAL MP EJECUTADAS EQC | P18: =+SUM(B16:M16) -> 65 | AC18: 12
A19: N° MP REPROGRAMADAS EQC | B19: =+COUNTIFS('CATASTRO Y PLANIFICACIÓN MP'!$O$16:$O$4951,"CRÍTICO",'CATASTRO Y PLANIFICACIÓN MP'!Y16:Y4951,"ꓣ") -> 0 | C19: =+COUNTIFS('CATASTRO Y PLANIFICACIÓN MP'!$O$16:$O$4951,"CRÍTICO",'CATASTRO Y PLANIFICACIÓN MP'!Z16:Z4951,"ꓣ") -> 0 | D19: =+COUNTIFS('CATASTRO Y PLANIFICACIÓN MP'!$O$16:$O$4951,"CRÍTICO",'CATASTRO Y PLANIFICACIÓN MP'!AA16:AA4951,"ꓣ") -> 0 | E19: =+COUNTIFS('CATASTRO Y PLANIFICACIÓN MP'!$O$16:$O$4951,"CRÍTICO",'CATASTRO Y PLANIFICACIÓN MP'!AB16:AB4951,"ꓣ") -> 0 | F19: =+COUNTIFS('CATASTRO Y PLANIFICACIÓN MP'!$O$16:$O$4951,"CRÍTICO",'CATASTRO Y PLANIFICACIÓN MP'!AC16:AC4951,"ꓣ") -> 0 | G19: =+COUNTIFS('CATASTRO Y PLANIFICACIÓN MP'!$O$16:$O$4951,"CRÍTICO",'CATASTRO Y PLANIFICACIÓN MP'!AD16:AD4951,"ꓣ") -> 0 | H19: =+COUNTIFS('CATASTRO Y PLANIFICACIÓN MP'!$O$16:$O$4951,"CRÍTICO",'CATASTRO Y PLANIFICACIÓN MP'!AE16:AE4951,"ꓣ") -> 0 | I19: =+COUNTIFS('CATASTRO Y PLANIFICACIÓN MP'!$O$16:$O$4951,"CRÍTICO",'CATASTRO Y PLANIFICACIÓN MP'!AF16:AF4951,"ꓣ") -> 0 | ... M19: =+COUNTIFS('CATASTRO Y PLANIFICACIÓN MP'!$O$16:$O$4951,"CRÍTICO",'CATASTRO Y PLANIFICACIÓN MP'!AJ16:AJ4951,"ꓣ") -> 0 | O19: TOTAL MP EJECUTADAS EQR | P19: =+SUM(B17:M17) -> 11 | S19: MANTENIMIENTO CORRECTIVO
A20: N° MP REPROGRAMADAS EQR | B20: =+COUNTIFS('CATASTRO Y PLANIFICACIÓN MP'!$O$16:$O$4951,"RELEVANTE",'CATASTRO Y PLANIFICACIÓN MP'!Y16:Y4951,"ꓣ") -> 0 | C20: =+COUNTIFS('CATASTRO Y PLANIFICACIÓN MP'!$O$16:$O$4951,"RELEVANTE",'CATASTRO Y PLANIFICACIÓN MP'!Z16:Z4951,"ꓣ") -> 0 | D20: =+COUNTIFS('CATASTRO Y PLANIFICACIÓN MP'!$O$16:$O$4951,"RELEVANTE",'CATASTRO Y PLANIFICACIÓN MP'!AA16:AA4951,"ꓣ") -> 0 | E20: =+COUNTIFS('CATASTRO Y PLANIFICACIÓN MP'!$O$16:$O$4951,"RELEVANTE",'CATASTRO Y PLANIFICACIÓN MP'!AB16:AB4951,"ꓣ") -> 0 | F20: =+COUNTIFS('CATASTRO Y PLANIFICACIÓN MP'!$O$16:$O$4951,"RELEVANTE",'CATASTRO Y PLANIFICACIÓN MP'!AC16:AC4951,"ꓣ") -> 0 | G20: =+COUNTIFS('CATASTRO Y PLANIFICACIÓN MP'!$O$16:$O$4951,"RELEVANTE",'CATASTRO Y PLANIFICACIÓN MP'!AD16:AD4951,"ꓣ") -> 0 | H20: =+COUNTIFS('CATASTRO Y PLANIFICACIÓN MP'!$O$16:$O$4951,"RELEVANTE",'CATASTRO Y PLANIFICACIÓN MP'!AE16:AE4951,"ꓣ") -> 0 | I20: =+COUNTIFS('CATASTRO Y PLANIFICACIÓN MP'!$O$16:$O$4951,"RELEVANTE",'CATASTRO Y PLANIFICACIÓN MP'!AF16:AF4951,"ꓣ") -> 0 | ... M20: =+COUNTIFS('CATASTRO Y PLANIFICACIÓN MP'!$O$16:$O$4951,"RELEVANTE",'CATASTRO Y PLANIFICACIÓN MP'!AJ16:AJ4951,"ꓣ") -> 0 | O20: TOTAL MP EJECUTADAS IM≥12 | P20: =+SUM(B18:M18) -> 0 | S20: ADQUISICIÓN DE REPUESTOS
A21: N° MP REPROGRAMADAS IM≥12 | B21: =+COUNTIFS('CATASTRO Y PLANIFICACIÓN MP'!$O$16:$O$4951,"IM ≥ 12",'CATASTRO Y PLANIFICACIÓN MP'!Y16:Y4951,"ꓣ") -> 0 | C21: =+COUNTIFS('CATASTRO Y PLANIFICACIÓN MP'!$O$16:$O$4951,"IM ≥ 12",'CATASTRO Y PLANIFICACIÓN MP'!Z16:Z4951,"ꓣ") -> 0 | D21: =+COUNTIFS('CATASTRO Y PLANIFICACIÓN MP'!$O$16:$O$4951,"IM ≥ 12",'CATASTRO Y PLANIFICACIÓN MP'!AA16:AA4951,"ꓣ") -> 0 | E21: =+COUNTIFS('CATASTRO Y PLANIFICACIÓN MP'!$O$16:$O$4951,"IM ≥ 12",'CATASTRO Y PLANIFICACIÓN MP'!AB16:AB4951,"ꓣ") -> 0 | F21: =+COUNTIFS('CATASTRO Y PLANIFICACIÓN MP'!$O$16:$O$4951,"IM ≥ 12",'CATASTRO Y PLANIFICACIÓN MP'!AC16:AC4951,"ꓣ") -> 0 | G21: =+COUNTIFS('CATASTRO Y PLANIFICACIÓN MP'!$O$16:$O$4951,"IM ≥ 12",'CATASTRO Y PLANIFICACIÓN MP'!AD16:AD4951,"ꓣ") -> 0 | H21: =+COUNTIFS('CATASTRO Y PLANIFICACIÓN MP'!$O$16:$O$4951,"IM ≥ 12",'CATASTRO Y PLANIFICACIÓN MP'!AE16:AE4951,"ꓣ") -> 0 | I21: =+COUNTIFS('CATASTRO Y PLANIFICACIÓN MP'!$O$16:$O$4951,"IM ≥ 12",'CATASTRO Y PLANIFICACIÓN MP'!AF16:AF4951,"ꓣ") -> 0 | ... M21: =+COUNTIFS('CATASTRO Y PLANIFICACIÓN MP'!$O$16:$O$4951,"IM ≥ 12",'CATASTRO Y PLANIFICACIÓN MP'!AJ16:AJ4951,"ꓣ") -> 0 | S21: ADQUISICIÓN DE INSUMOS
O22: INDICADOR | P22: NIVEL ALCANZADO | S22: ADQUISICION DE ACCESORIOS
O23: % EJECUCION ANUAL MP | P23: =+P13/P12 -> 7.6
A24: % EJECUCIÓN MP TOTAL MENSUAL | B24: =+IFERROR(B13/(B13+B14),"") -> 1 | C24: =+IFERROR(C13/(C13+C14),"") | D24: =+IFERROR(D13/(D13+D14),"") | E24: =+IFERROR(E13/(E13+E14),"") | F24: =+IFERROR(F13/(F13+F14),"") | G24: =+IFERROR(G13/(G13+G14),"") | H24: =+IFERROR(H13/(H13+H14),"") | I24: =+IFERROR(I13/(I13+I14),"") | ... M24: =+IFERROR(M13/(M13+M14),"") | O24: % EJECUCIÓN ANUAL EQC | P24: =+P18/P15 -> 10.833333
A25: % EJECUCIÓN MP EQC MENSUAL | B25: =+IFERROR(B16/(B16+B19),"") -> 1 | C25: =+IFERROR(C16/(C16+C19),"") | D25: =+IFERROR(D16/(D16+D19),"") | E25: =+IFERROR(E16/(E16+E19),"") | F25: =+IFERROR(F16/(F16+F19),"") | G25: =+IFERROR(G16/(G16+G19),"") | H25: =+IFERROR(H16/(H16+H19),"") | I25: =+IFERROR(I16/(I16+I19),"") | ... M25: =+IFERROR(M16/(M16+M19),"") | O25: % EJECUCIÓN ANUAL EQR | P25: =+P19/P16 -> 11
A26: % EJECUCIÓN MP EQR MENSUAL | B26: =+IFERROR(B17/(B17+B20),"") -> 1 | C26: =+IFERROR(C17/(C17+C20),"") | D26: =+IFERROR(D17/(D17+D20),"") | E26: =+IFERROR(E17/(E17+E20),"") | F26: =+IFERROR(F17/(F17+F20),"") | G26: =+IFERROR(G17/(G17+G20),"") | H26: =+IFERROR(H17/(H17+H20),"") | I26: =+IFERROR(I17/(I17+I20),"") | ... M26: =+IFERROR(M17/(M17+M20),"") | O26: % EJECUCIÓN ANUAL IM≥12 | P26: =+P20/P17 -> 0
A27: % EJECUCIÓN MP IM≥12 MENSUAL | B27: =+IFERROR(B18/(B18+B21),"") | C27: =+IFERROR(C18/(C18+C21),"") | D27: =+IFERROR(D18/(D18+D21),"") | E27: =+IFERROR(E18/(E18+E21),"") | F27: =+IFERROR(F18/(F18+F21),"") | G27: =+IFERROR(G18/(G18+G21),"") | H27: =+IFERROR(H18/(H18+H21),"") | I27: =+IFERROR(I18/(I18+I21),"") | ... M27: =+IFERROR(M18/(M18+M21),"")
A29: GASTO PROGRAMADO MP | B29: =+SUM('SEGUIMIENTO GASTO'!I8:I140) -> 705485554
A31: GASTO PROGRAMADO MC | B31: =+'CATASTRO Y PLANIFICACIÓN MP'!B13 -> 400000000
A33: EJECUCIÓN GASTO MP | B33: =+SUM('SEGUIMIENTO GASTO'!AI8:AI141) -> 97382016
A35: EJECUCIÓN GASTO MC | B35: =+SUM('SEGUIMIENTO GASTO'!AG149:AG235) -> 15588666
A37: % EJECUCIÓN DEL GASTO MP | B37: =+IFERROR(B33/B29,"") -> 0.13803545 | D37: =1-B37 -> 0.86196455
A39: % EJECUCIÓN DEL GASTO MC | B39: =+IFERROR(B35/B31,"") -> 0.038971665 | D39: =1-B39 -> 0.96102833
A42: Etiquetas de fila | B42: Suma de COSTO ANUAL DE MANTENIMIENTO SEGÚN CONVENIO / PRECIO DE REFERENCIA MANTENIMIENTO ANUAL
A43: 2023 | B43: 4650000
A44: 2024 | B44: 1250000
A45: 2025 | B45: 78000000
A46: (en blanco)
A47: Total general | B47: 83900000
A49: Etiquetas de fila | B49: Suma de FRECUENCIA ANUAL DE MANTENIMIENTO
A50: 2023 | B50: 10
A51: CRÍTICO | B51: 6
A52: IM ≥ 12 | B52: 3
A53: RELEVANTE | B53: 1
A54: 2024 | B54: 4
A55: IM ≥ 12 | B55: 3
A56: RELEVANTE | B56: 1
A57: 2025 | B57: 1
A58: RELEVANTE | B58: 1
A59: (en blanco)
A60: (en blanco)
A61: Total general | B61: 15
